{
  "20191": {
    "CAUTION": {
      "(~2018학번)국제캠퍼스": {
        "필수교양-자연과우주": [
          "[권장수강대상] 이과대학, 생명시스템대학 소속 학과 1학년",
          "상대평가"
        ]
      },
      "국제캠퍼스(2019학번~)": {
        "대학교양-자연과우주": [
          "[권장수강대상] 이과대학, 생명시스템대학 소속 학과 1학년",
          "상대평가"
        ]
      }
    },
    "LECT_DATA": {
      "학정번호-분반-실습": "PHY1001-04-00",
      "과목명": "일반물리학및실험(1)",
      "학점": "3",
      "담당교수": "주홍렬",
      "강의시간": "월3,4(수3,4)",
      "강의실": "I진A202(I자B326)",
      "정원": "1",
      "참여인원": "1",
      "전공자정원": "0",
      "2전공포함": "N",
      "1학년정원": "0",
      "2학년정원": "0",
      "3학년정원": "0",
      "4학년정원": "0",
      "교환학생 가능여부": "X",
      "Max Mileage(limit)": "36",
      "Mileage_minimum": "5",
      "Mileage_maximum": "5",
      "Mileage_average": "5"
    },
    "RESULT_DATA": [
      {
        "순위": "1",
        "마일리지": "5",
        "전공자/복수전공자": "N",
        "전공자정원포함여부": "N",
        "신청과목수": "6",
        "졸업신청": "N",
        "초수강여부": "N",
        "총이수학점/졸업이수학점": "0.5481",
        "직전학기이수학점/학기당수강학점": "0.9736",
        "학년": "3",
        "수강여부": "O",
        "비고": ""
      }
    ]
  },
  "20201": {
    "CAUTION": {
      "(~2018학번)국제캠퍼스": {
        "필수교양-자연과우주": [
          "영어강의",
          "절대평가"
        ]
      },
      "국제캠퍼스(2019학번~)": {
        "대학교양-자연과우주": [
          "영어강의",
          "절대평가"
        ]
      }
    },
    "LECT_DATA": {
      "학정번호-분반-실습": "PHY1001-04-00",
      "과목명": "일반물리학및실험(1)",
      "학점": "3",
      "담당교수": "여인환",
      "강의시간": "월5,6(수5,6)",
      "강의실": "I진A202(I자B326)",
      "정원": "1",
      "참여인원": "1",
      "전공자정원": "0",
      "2전공포함": "N",
      "1학년정원": "0",
      "2학년정원": "0",
      "3학년정원": "0",
      "4학년정원": "0",
      "교환학생 가능여부": "X",
      "Max Mileage(limit)": "36",
      "Mileage_minimum": "8",
      "Mileage_maximum": "8",
      "Mileage_average": "8"
    },
    "RESULT_DATA": [
      {
        "순위": "1",
        "마일리지": "8",
        "전공자/복수전공자": "N",
        "전공자정원포함여부": "N",
        "신청과목수": "6",
        "졸업신청": "Y",
        "초수강여부": "Y",
        "총이수학점/졸업이수학점": "1.0000",
        "직전학기이수학점/학기당수강학점": "1.0000",
        "학년": "4",
        "수강여부": "O",
        "비고": ""
      }
    ]
  }
}