{
  "20192": {
    "CAUTION": {
      "필수교양(10~18학번)": {
        "가치와윤리": [
          "절대평가"
        ]
      },
      "대학교양(2019학번~)": {
        "가치와윤리": [
          "절대평가"
        ]
      }
    },
    "LECT_DATA": {
      "학정번호-분반-실습": "YCG1704-01-00",
      "과목명": "기독교와서구문명",
      "학점": "3",
      "담당교수": "윤혜준,박민성",
      "강의시간": "목7,8,9",
      "강의실": "교403",
      "정원": "92",
      "참여인원": "76",
      "전공자정원": "0",
      "2전공포함": "N",
      "1학년정원": "0",
      "2학년정원": "31",
      "3학년정원": "30",
      "4학년정원": "31",
      "교환학생 가능여부": "O",
      "Max Mileage(limit)": "36",
      "Mileage_minimum": "1",
      "Mileage_maximum": "36",
      "Mileage_average": "13.83"
    },
    "RESULT_DATA": [
      {
        "순위": "1",
        "마일리지": "36",
        "전공자/복수전공자": "N",
        "전공자정원포함여부": "N",
        "신청과목수": "6",
        "졸업신청": "Y",
        "초수강여부": "Y",
        "총이수학점/졸업이수학점": "0.9444",
        "직전학기이수학점/학기당수강학점": "0.8333",
        "학년": "4",
        "수강여부": "O",
        "비고": ""
      },
      {
        "순위": "2",
        "마일리지": "36",
        "전공자/복수전공자": "N",
        "전공자정원포함여부": "N",
        "신청과목수": "6",
        "졸업신청": "N",
        "초수강여부": "Y",
        "총이수학점/졸업이수학점": "0.6592",
        "직전학기이수학점/학기당수강학점": "0.9473",
        "학년": "3",
        "수강여부": "O",
        "비고": ""
      },
      {
        "순위": "3",
        "마일리지": "36",
        "전공자/복수전공자": "N",
        "전공자정원포함여부": "N",
        "신청과목수": "6",
        "졸업신청": "N",
        "초수강여부": "Y",
        "총이수학점/졸업이수학점": "0.4107",
        "직전학기이수학점/학기당수강학점": "0.9736",
        "학년": "2",
        "수강여부": "O",
        "비고": ""
      },
      {
        "순위": "4",
        "마일리지": "36",
        "전공자/복수전공자": "N",
        "전공자정원포함여부": "N",
        "신청과목수": "6",
        "졸업신청": "N",
        "초수강여부": "Y",
        "총이수학점/졸업이수학점": "0.3964",
        "직전학기이수학점/학기당수강학점": "0.9736",
        "학년": "2",
        "수강여부": "O",
        "비고": ""
      },
      {
        "순위": "5",
        "마일리지": "36",
        "전공자/복수전공자": "N",
        "전공자정원포함여부": "N",
        "신청과목수": "6",
        "졸업신청": "N",
        "초수강여부": "Y",
        "총이수학점/졸업이수학점": "0.3785",
        "직전학기이수학점/학기당수강학점": "0.9736",
        "학년": "2",
        "수강여부": "O",
        "비고": ""
      },
      {
        "순위": "6",
        "마일리지": "36",
        "전공자/복수전공자": "N",
        "전공자정원포함여부": "N",
        "신청과목수": "1",
        "졸업신청": "Y",
        "초수강여부": "Y",
        "총이수학점/졸업이수학점": "0.9920",
        "직전학기이수학점/학기당수강학점": "0.8333",
        "학년": "4",
        "수강여부": "O",
        "비고": ""
      },
      {
        "순위": "7",
        "마일리지": "35",
        "전공자/복수전공자": "N",
        "전공자정원포함여부": "N",
        "신청과목수": "6",
        "졸업신청": "N",
        "초수강여부": "Y",
        "총이수학점/졸업이수학점": "0.7565",
        "직전학기이수학점/학기당수강학점": "0.4791",
        "학년": "2",
        "수강여부": "O",
        "비고": ""
      },
      {
        "순위": "8",
        "마일리지": "34",
        "전공자/복수전공자": "N",
        "전공자정원포함여부": "N",
        "신청과목수": "6",
        "졸업신청": "N",
        "초수강여부": "Y",
        "총이수학점/졸업이수학점": "0.8650",
        "직전학기이수학점/학기당수강학점": "0.8333",
        "학년": "4",
        "수강여부": "O",
        "비고": ""
      },
      {
        "순위": "9",
        "마일리지": "34",
        "전공자/복수전공자": "N",
        "전공자정원포함여부": "N",
        "신청과목수": "6",
        "졸업신청": "N",
        "초수강여부": "Y",
        "총이수학점/졸업이수학점": "0.3785",
        "직전학기이수학점/학기당수강학점": "0.9736",
        "학년": "2",
        "수강여부": "O",
        "비고": ""
      },
      {
        "순위": "10",
        "마일리지": "32",
        "전공자/복수전공자": "N",
        "전공자정원포함여부": "N",
        "신청과목수": "6",
        "졸업신청": "N",
        "초수강여부": "Y",
        "총이수학점/졸업이수학점": "0.6214",
        "직전학기이수학점/학기당수강학점": "1.0000",
        "학년": "3",
        "수강여부": "O",
        "비고": ""
      },
      {
        "순위": "11",
        "마일리지": "31",
        "전공자/복수전공자": "N",
        "전공자정원포함여부": "N",
        "신청과목수": "6",
        "졸업신청": "N",
        "초수강여부": "Y",
        "총이수학점/졸업이수학점": "0.4250",
        "직전학기이수학점/학기당수강학점": "1.0000",
        "학년": "2",
        "수강여부": "O",
        "비고": ""
      },
      {
        "순위": "12",
        "마일리지": "31",
        "전공자/복수전공자": "N",
        "전공자정원포함여부": "N",
        "신청과목수": "6",
        "졸업신청": "N",
        "초수강여부": "Y",
        "총이수학점/졸업이수학점": "0.4087",
        "직전학기이수학점/학기당수강학점": "0.8611",
        "학년": "2",
        "수강여부": "O",
        "비고": ""
      },
      {
        "순위": "13",
        "마일리지": "30",
        "전공자/복수전공자": "N",
        "전공자정원포함여부": "N",
        "신청과목수": "6",
        "졸업신청": "N",
        "초수강여부": "Y",
        "총이수학점/졸업이수학점": "0.7714",
        "직전학기이수학점/학기당수강학점": "0.9736",
        "학년": "4",
        "수강여부": "O",
        "비고": ""
      },
      {
        "순위": "14",
        "마일리지": "30",
        "전공자/복수전공자": "N",
        "전공자정원포함여부": "N",
        "신청과목수": "6",
        "졸업신청": "N",
        "초수강여부": "Y",
        "총이수학점/졸업이수학점": "0.6349",
        "직전학기이수학점/학기당수강학점": "1.0000",
        "학년": "3",
        "수강여부": "O",
        "비고": ""
      },
      {
        "순위": "15",
        "마일리지": "30",
        "전공자/복수전공자": "N",
        "전공자정원포함여부": "N",
        "신청과목수": "6",
        "졸업신청": "N",
        "초수강여부": "Y",
        "총이수학점/졸업이수학점": "0.4126",
        "직전학기이수학점/학기당수강학점": "0.8888",
        "학년": "2",
        "수강여부": "O",
        "비고": ""
      },
      {
        "순위": "16",
        "마일리지": "28",
        "전공자/복수전공자": "N",
        "전공자정원포함여부": "N",
        "신청과목수": "6",
        "졸업신청": "N",
        "초수강여부": "Y",
        "총이수학점/졸업이수학점": "0.4087",
        "직전학기이수학점/학기당수강학점": "1.0000",
        "학년": "2",
        "수강여부": "O",
        "비고": ""
      },
      {
        "순위": "17",
        "마일리지": "27",
        "전공자/복수전공자": "N",
        "전공자정원포함여부": "N",
        "신청과목수": "6",
        "졸업신청": "N",
        "초수강여부": "Y",
        "총이수학점/졸업이수학점": "0.3571",
        "직전학기이수학점/학기당수강학점": "0.8888",
        "학년": "2",
        "수강여부": "O",
        "비고": ""
      },
      {
        "순위": "18",
        "마일리지": "25",
        "전공자/복수전공자": "N",
        "전공자정원포함여부": "N",
        "신청과목수": "6",
        "졸업신청": "N",
        "초수강여부": "Y",
        "총이수학점/졸업이수학점": "0.4259",
        "직전학기이수학점/학기당수강학점": "0.9736",
        "학년": "2",
        "수강여부": "O",
        "비고": ""
      },
      {
        "순위": "19",
        "마일리지": "23",
        "전공자/복수전공자": "N",
        "전공자정원포함여부": "N",
        "신청과목수": "6",
        "졸업신청": "Y",
        "초수강여부": "Y",
        "총이수학점/졸업이수학점": "0.9285",
        "직전학기이수학점/학기당수강학점": "0.8333",
        "학년": "4",
        "수강여부": "O",
        "비고": ""
      },
      {
        "순위": "20",
        "마일리지": "23",
        "전공자/복수전공자": "N",
        "전공자정원포함여부": "N",
        "신청과목수": "6",
        "졸업신청": "N",
        "초수강여부": "Y",
        "총이수학점/졸업이수학점": "0.2571",
        "직전학기이수학점/학기당수강학점": "0.8947",
        "학년": "2",
        "수강여부": "O",
        "비고": ""
      },
      {
        "순위": "21",
        "마일리지": "22",
        "전공자/복수전공자": "N",
        "전공자정원포함여부": "N",
        "신청과목수": "6",
        "졸업신청": "N",
        "초수강여부": "Y",
        "총이수학점/졸업이수학점": "0.4007",
        "직전학기이수학점/학기당수강학점": "1.0000",
        "학년": "2",
        "수강여부": "O",
        "비고": ""
      },
      {
        "순위": "22",
        "마일리지": "22",
        "전공자/복수전공자": "N",
        "전공자정원포함여부": "N",
        "신청과목수": "6",
        "졸업신청": "N",
        "초수강여부": "Y",
        "총이수학점/졸업이수학점": "0.3607",
        "직전학기이수학점/학기당수강학점": "0.9736",
        "학년": "2",
        "수강여부": "O",
        "비고": ""
      },
      {
        "순위": "23",
        "마일리지": "22",
        "전공자/복수전공자": "N",
        "전공자정원포함여부": "N",
        "신청과목수": "4",
        "졸업신청": "N",
        "초수강여부": "Y",
        "총이수학점/졸업이수학점": "0.8157",
        "직전학기이수학점/학기당수강학점": "0.8750",
        "학년": "2",
        "수강여부": "O",
        "비고": ""
      },
      {
        "순위": "24",
        "마일리지": "22",
        "전공자/복수전공자": "N",
        "전공자정원포함여부": "N",
        "신청과목수": "3",
        "졸업신청": "N",
        "초수강여부": "Y",
        "총이수학점/졸업이수학점": "0.9841",
        "직전학기이수학점/학기당수강학점": "0.5000",
        "학년": "4",
        "수강여부": "O",
        "비고": ""
      },
      {
        "순위": "25",
        "마일리지": "21",
        "전공자/복수전공자": "N",
        "전공자정원포함여부": "N",
        "신청과목수": "6",
        "졸업신청": "N",
        "초수강여부": "Y",
        "총이수학점/졸업이수학점": "0.2666",
        "직전학기이수학점/학기당수강학점": "1.0000",
        "학년": "2",
        "수강여부": "O",
        "비고": ""
      },
      {
        "순위": "26",
        "마일리지": "18",
        "전공자/복수전공자": "N",
        "전공자정원포함여부": "N",
        "신청과목수": "6",
        "졸업신청": "N",
        "초수강여부": "Y",
        "총이수학점/졸업이수학점": "0.7936",
        "직전학기이수학점/학기당수강학점": "0.6944",
        "학년": "4",
        "수강여부": "O",
        "비고": ""
      },
      {
        "순위": "27",
        "마일리지": "16",
        "전공자/복수전공자": "N",
        "전공자정원포함여부": "N",
        "신청과목수": "6",
        "졸업신청": "N",
        "초수강여부": "Y",
        "총이수학점/졸업이수학점": "0.7259",
        "직전학기이수학점/학기당수강학점": "1.0000",
        "학년": "4",
        "수강여부": "O",
        "비고": ""
      },
      {
        "순위": "28",
        "마일리지": "15",
        "전공자/복수전공자": "N",
        "전공자정원포함여부": "N",
        "신청과목수": "5",
        "졸업신청": "N",
        "초수강여부": "Y",
        "총이수학점/졸업이수학점": "0.3928",
        "직전학기이수학점/학기당수강학점": "0.9166",
        "학년": "2",
        "수강여부": "O",
        "비고": ""
      },
      {
        "순위": "29",
        "마일리지": "13",
        "전공자/복수전공자": "N",
        "전공자정원포함여부": "N",
        "신청과목수": "6",
        "졸업신청": "N",
        "초수강여부": "Y",
        "총이수학점/졸업이수학점": "0.7698",
        "직전학기이수학점/학기당수강학점": "0.8333",
        "학년": "4",
        "수강여부": "O",
        "비고": ""
      },
      {
        "순위": "30",
        "마일리지": "13",
        "전공자/복수전공자": "N",
        "전공자정원포함여부": "N",
        "신청과목수": "6",
        "졸업신청": "N",
        "초수강여부": "Y",
        "총이수학점/졸업이수학점": "0.3928",
        "직전학기이수학점/학기당수강학점": "0.9166",
        "학년": "2",
        "수강여부": "O",
        "비고": ""
      },
      {
        "순위": "31",
        "마일리지": "12",
        "전공자/복수전공자": "N",
        "전공자정원포함여부": "N",
        "신청과목수": "6",
        "졸업신청": "N",
        "초수강여부": "Y",
        "총이수학점/졸업이수학점": "0.4206",
        "직전학기이수학점/학기당수강학점": "0.8333",
        "학년": "3",
        "수강여부": "O",
        "비고": ""
      },
      {
        "순위": "32",
        "마일리지": "12",
        "전공자/복수전공자": "N",
        "전공자정원포함여부": "N",
        "신청과목수": "5",
        "졸업신청": "N",
        "초수강여부": "Y",
        "총이수학점/졸업이수학점": "0.8571",
        "직전학기이수학점/학기당수강학점": "0.8333",
        "학년": "4",
        "수강여부": "O",
        "비고": ""
      },
      {
        "순위": "33",
        "마일리지": "12",
        "전공자/복수전공자": "N",
        "전공자정원포함여부": "N",
        "신청과목수": "5",
        "졸업신청": "N",
        "초수강여부": "Y",
        "총이수학점/졸업이수학점": "0.4126",
        "직전학기이수학점/학기당수강학점": "1.0000",
        "학년": "2",
        "수강여부": "O",
        "비고": ""
      },
      {
        "순위": "34",
        "마일리지": "11",
        "전공자/복수전공자": "N",
        "전공자정원포함여부": "N",
        "신청과목수": "6",
        "졸업신청": "N",
        "초수강여부": "Y",
        "총이수학점/졸업이수학점": "0.7063",
        "직전학기이수학점/학기당수강학점": "1.0000",
        "학년": "3",
        "수강여부": "O",
        "비고": ""
      },
      {
        "순위": "35",
        "마일리지": "10",
        "전공자/복수전공자": "N",
        "전공자정원포함여부": "N",
        "신청과목수": "6",
        "졸업신청": "N",
        "초수강여부": "Y",
        "총이수학점/졸업이수학점": "0.5714",
        "직전학기이수학점/학기당수강학점": "1.0000",
        "학년": "3",
        "수강여부": "O",
        "비고": ""
      },
      {
        "순위": "36",
        "마일리지": "10",
        "전공자/복수전공자": "N",
        "전공자정원포함여부": "N",
        "신청과목수": "6",
        "졸업신청": "N",
        "초수강여부": "Y",
        "총이수학점/졸업이수학점": "0.4801",
        "직전학기이수학점/학기당수강학점": "1.0000",
        "학년": "2",
        "수강여부": "O",
        "비고": ""
      },
      {
        "순위": "37",
        "마일리지": "10",
        "전공자/복수전공자": "N",
        "전공자정원포함여부": "N",
        "신청과목수": "6",
        "졸업신청": "N",
        "초수강여부": "Y",
        "총이수학점/졸업이수학점": "0.4484",
        "직전학기이수학점/학기당수강학점": "1.0000",
        "학년": "2",
        "수강여부": "O",
        "비고": ""
      },
      {
        "순위": "38",
        "마일리지": "10",
        "전공자/복수전공자": "N",
        "전공자정원포함여부": "N",
        "신청과목수": "6",
        "졸업신청": "N",
        "초수강여부": "Y",
        "총이수학점/졸업이수학점": "0.4285",
        "직전학기이수학점/학기당수강학점": "0.6315",
        "학년": "3",
        "수강여부": "O",
        "비고": ""
      },
      {
        "순위": "39",
        "마일리지": "10",
        "전공자/복수전공자": "N",
        "전공자정원포함여부": "N",
        "신청과목수": "5",
        "졸업신청": "N",
        "초수강여부": "Y",
        "총이수학점/졸업이수학점": "0.6666",
        "직전학기이수학점/학기당수강학점": "1.0000",
        "학년": "3",
        "수강여부": "O",
        "비고": ""
      },
      {
        "순위": "40",
        "마일리지": "10",
        "전공자/복수전공자": "N",
        "전공자정원포함여부": "N",
        "신청과목수": "5",
        "졸업신청": "N",
        "초수강여부": "Y",
        "총이수학점/졸업이수학점": "0.2777",
        "직전학기이수학점/학기당수강학점": "1.0000",
        "학년": "2",
        "수강여부": "O",
        "비고": ""
      },
      {
        "순위": "41",
        "마일리지": "10",
        "전공자/복수전공자": "N",
        "전공자정원포함여부": "N",
        "신청과목수": "4",
        "졸업신청": "Y",
        "초수강여부": "Y",
        "총이수학점/졸업이수학점": "0.9047",
        "직전학기이수학점/학기당수강학점": "0.6666",
        "학년": "4",
        "수강여부": "O",
        "비고": ""
      },
      {
        "순위": "42",
        "마일리지": "9",
        "전공자/복수전공자": "N",
        "전공자정원포함여부": "N",
        "신청과목수": "6",
        "졸업신청": "N",
        "초수강여부": "Y",
        "총이수학점/졸업이수학점": "0.7222",
        "직전학기이수학점/학기당수강학점": "1.0000",
        "학년": "3",
        "수강여부": "O",
        "비고": ""
      },
      {
        "순위": "43",
        "마일리지": "8",
        "전공자/복수전공자": "N",
        "전공자정원포함여부": "N",
        "신청과목수": "6",
        "졸업신청": "N",
        "초수강여부": "Y",
        "총이수학점/졸업이수학점": "0.7697",
        "직전학기이수학점/학기당수강학점": "0.6041",
        "학년": "2",
        "수강여부": "O",
        "비고": ""
      },
      {
        "순위": "44",
        "마일리지": "8",
        "전공자/복수전공자": "N",
        "전공자정원포함여부": "N",
        "신청과목수": "6",
        "졸업신청": "N",
        "초수강여부": "Y",
        "총이수학점/졸업이수학점": "0.7214",
        "직전학기이수학점/학기당수강학점": "0.9473",
        "학년": "4",
        "수강여부": "O",
        "비고": ""
      },
      {
        "순위": "45",
        "마일리지": "8",
        "전공자/복수전공자": "N",
        "전공자정원포함여부": "N",
        "신청과목수": "6",
        "졸업신청": "N",
        "초수강여부": "Y",
        "총이수학점/졸업이수학점": "0.4047",
        "직전학기이수학점/학기당수강학점": "0.8684",
        "학년": "2",
        "수강여부": "O",
        "비고": ""
      },
      {
        "순위": "46",
        "마일리지": "8",
        "전공자/복수전공자": "N",
        "전공자정원포함여부": "N",
        "신청과목수": "6",
        "졸업신청": "N",
        "초수강여부": "Y",
        "총이수학점/졸업이수학점": "0.3968",
        "직전학기이수학점/학기당수강학점": "0.8333",
        "학년": "2",
        "수강여부": "O",
        "비고": ""
      },
      {
        "순위": "47",
        "마일리지": "7",
        "전공자/복수전공자": "N",
        "전공자정원포함여부": "N",
        "신청과목수": "6",
        "졸업신청": "N",
        "초수강여부": "Y",
        "총이수학점/졸업이수학점": "0.4087",
        "직전학기이수학점/학기당수강학점": "1.0000",
        "학년": "2",
        "수강여부": "O",
        "비고": ""
      },
      {
        "순위": "48",
        "마일리지": "6",
        "전공자/복수전공자": "N",
        "전공자정원포함여부": "N",
        "신청과목수": "6",
        "졸업신청": "N",
        "초수강여부": "Y",
        "총이수학점/졸업이수학점": "0.4087",
        "직전학기이수학점/학기당수강학점": "0.8611",
        "학년": "2",
        "수강여부": "O",
        "비고": ""
      },
      {
        "순위": "49",
        "마일리지": "5",
        "전공자/복수전공자": "N",
        "전공자정원포함여부": "N",
        "신청과목수": "6",
        "졸업신청": "Y",
        "초수강여부": "Y",
        "총이수학점/졸업이수학점": "0.9142",
        "직전학기이수학점/학기당수강학점": "0.9473",
        "학년": "4",
        "수강여부": "O",
        "비고": ""
      },
      {
        "순위": "50",
        "마일리지": "5",
        "전공자/복수전공자": "N",
        "전공자정원포함여부": "N",
        "신청과목수": "6",
        "졸업신청": "N",
        "초수강여부": "Y",
        "총이수학점/졸업이수학점": "0.6527",
        "직전학기이수학점/학기당수강학점": "0.8611",
        "학년": "3",
        "수강여부": "O",
        "비고": ""
      },
      {
        "순위": "51",
        "마일리지": "5",
        "전공자/복수전공자": "N",
        "전공자정원포함여부": "N",
        "신청과목수": "6",
        "졸업신청": "N",
        "초수강여부": "Y",
        "총이수학점/졸업이수학점": "0.6408",
        "직전학기이수학점/학기당수강학점": "0.8611",
        "학년": "3",
        "수강여부": "O",
        "비고": ""
      },
      {
        "순위": "52",
        "마일리지": "5",
        "전공자/복수전공자": "N",
        "전공자정원포함여부": "N",
        "신청과목수": "6",
        "졸업신청": "N",
        "초수강여부": "Y",
        "총이수학점/졸업이수학점": "0.4642",
        "직전학기이수학점/학기당수강학점": "1.0000",
        "학년": "2",
        "수강여부": "O",
        "비고": ""
      },
      {
        "순위": "53",
        "마일리지": "5",
        "전공자/복수전공자": "N",
        "전공자정원포함여부": "N",
        "신청과목수": "6",
        "졸업신청": "N",
        "초수강여부": "Y",
        "총이수학점/졸업이수학점": "0.3849",
        "직전학기이수학점/학기당수강학점": "0.8611",
        "학년": "2",
        "수강여부": "O",
        "비고": ""
      },
      {
        "순위": "54",
        "마일리지": "5",
        "전공자/복수전공자": "N",
        "전공자정원포함여부": "N",
        "신청과목수": "6",
        "졸업신청": "N",
        "초수강여부": "Y",
        "총이수학점/졸업이수학점": "0.2698",
        "직전학기이수학점/학기당수강학점": "0.9444",
        "학년": "2",
        "수강여부": "O",
        "비고": ""
      },
      {
        "순위": "55",
        "마일리지": "4",
        "전공자/복수전공자": "N",
        "전공자정원포함여부": "N",
        "신청과목수": "6",
        "졸업신청": "N",
        "초수강여부": "Y",
        "총이수학점/졸업이수학점": "0.4960",
        "직전학기이수학점/학기당수강학점": "1.0000",
        "학년": "2",
        "수강여부": "O",
        "비고": ""
      },
      {
        "순위": "56",
        "마일리지": "4",
        "전공자/복수전공자": "N",
        "전공자정원포함여부": "N",
        "신청과목수": "6",
        "졸업신청": "N",
        "초수강여부": "Y",
        "총이수학점/졸업이수학점": "0.4087",
        "직전학기이수학점/학기당수강학점": "0.8611",
        "학년": "2",
        "수강여부": "X",
        "비고": ""
      },
      {
        "순위": "57",
        "마일리지": "4",
        "전공자/복수전공자": "N",
        "전공자정원포함여부": "N",
        "신청과목수": "6",
        "졸업신청": "N",
        "초수강여부": "Y",
        "총이수학점/졸업이수학점": "0.4007",
        "직전학기이수학점/학기당수강학점": "0.8611",
        "학년": "2",
        "수강여부": "X",
        "비고": ""
      },
      {
        "순위": "58",
        "마일리지": "3",
        "전공자/복수전공자": "N",
        "전공자정원포함여부": "N",
        "신청과목수": "6",
        "졸업신청": "N",
        "초수강여부": "Y",
        "총이수학점/졸업이수학점": "0.5238",
        "직전학기이수학점/학기당수강학점": "0.8611",
        "학년": "3",
        "수강여부": "O",
        "비고": ""
      },
      {
        "순위": "59",
        "마일리지": "2",
        "전공자/복수전공자": "N",
        "전공자정원포함여부": "N",
        "신청과목수": "6",
        "졸업신청": "Y",
        "초수강여부": "Y",
        "총이수학점/졸업이수학점": "0.8785",
        "직전학기이수학점/학기당수강학점": "0.9473",
        "학년": "4",
        "수강여부": "O",
        "비고": ""
      },
      {
        "순위": "60",
        "마일리지": "2",
        "전공자/복수전공자": "N",
        "전공자정원포함여부": "N",
        "신청과목수": "6",
        "졸업신청": "N",
        "초수강여부": "Y",
        "총이수학점/졸업이수학점": "0.4563",
        "직전학기이수학점/학기당수강학점": "1.0000",
        "학년": "2",
        "수강여부": "X",
        "비고": ""
      },
      {
        "순위": "61",
        "마일리지": "2",
        "전공자/복수전공자": "N",
        "전공자정원포함여부": "N",
        "신청과목수": "6",
        "졸업신청": "N",
        "초수강여부": "Y",
        "총이수학점/졸업이수학점": "0.3888",
        "직전학기이수학점/학기당수강학점": "0.8333",
        "학년": "2",
        "수강여부": "X",
        "비고": ""
      },
      {
        "순위": "62",
        "마일리지": "2",
        "전공자/복수전공자": "N",
        "전공자정원포함여부": "N",
        "신청과목수": "5",
        "졸업신청": "N",
        "초수강여부": "Y",
        "총이수학점/졸업이수학점": "0.3730",
        "직전학기이수학점/학기당수강학점": "0.8888",
        "학년": "2",
        "수강여부": "X",
        "비고": ""
      },
      {
        "순위": "63",
        "마일리지": "1",
        "전공자/복수전공자": "N",
        "전공자정원포함여부": "N",
        "신청과목수": "6",
        "졸업신청": "Y",
        "초수강여부": "Y",
        "총이수학점/졸업이수학점": "1.0000",
        "직전학기이수학점/학기당수강학점": "0.4210",
        "학년": "4",
        "수강여부": "O",
        "비고": ""
      },
      {
        "순위": "64",
        "마일리지": "1",
        "전공자/복수전공자": "N",
        "전공자정원포함여부": "N",
        "신청과목수": "6",
        "졸업신청": "Y",
        "초수강여부": "Y",
        "총이수학점/졸업이수학점": "0.9175",
        "직전학기이수학점/학기당수강학점": "1.0000",
        "학년": "4",
        "수강여부": "O",
        "비고": ""
      },
      {
        "순위": "65",
        "마일리지": "1",
        "전공자/복수전공자": "N",
        "전공자정원포함여부": "N",
        "신청과목수": "6",
        "졸업신청": "Y",
        "초수강여부": "Y",
        "총이수학점/졸업이수학점": "0.8214",
        "직전학기이수학점/학기당수강학점": "0.9473",
        "학년": "4",
        "수강여부": "O",
        "비고": ""
      },
      {
        "순위": "66",
        "마일리지": "1",
        "전공자/복수전공자": "N",
        "전공자정원포함여부": "N",
        "신청과목수": "6",
        "졸업신청": "N",
        "초수강여부": "Y",
        "총이수학점/졸업이수학점": "0.7936",
        "직전학기이수학점/학기당수강학점": "0.6666",
        "학년": "4",
        "수강여부": "O",
        "비고": ""
      },
      {
        "순위": "67",
        "마일리지": "1",
        "전공자/복수전공자": "N",
        "전공자정원포함여부": "N",
        "신청과목수": "6",
        "졸업신청": "N",
        "초수강여부": "Y",
        "총이수학점/졸업이수학점": "0.7388",
        "직전학기이수학점/학기당수강학점": "0.8157",
        "학년": "4",
        "수강여부": "O",
        "비고": ""
      },
      {
        "순위": "68",
        "마일리지": "1",
        "전공자/복수전공자": "N",
        "전공자정원포함여부": "N",
        "신청과목수": "6",
        "졸업신청": "N",
        "초수강여부": "Y",
        "총이수학점/졸업이수학점": "0.5821",
        "직전학기이수학점/학기당수강학점": "0.9736",
        "학년": "3",
        "수강여부": "O",
        "비고": ""
      },
      {
        "순위": "69",
        "마일리지": "1",
        "전공자/복수전공자": "N",
        "전공자정원포함여부": "N",
        "신청과목수": "6",
        "졸업신청": "N",
        "초수강여부": "Y",
        "총이수학점/졸업이수학점": "0.5714",
        "직전학기이수학점/학기당수강학점": "0.9736",
        "학년": "3",
        "수강여부": "O",
        "비고": ""
      },
      {
        "순위": "70",
        "마일리지": "1",
        "전공자/복수전공자": "N",
        "전공자정원포함여부": "N",
        "신청과목수": "6",
        "졸업신청": "N",
        "초수강여부": "Y",
        "총이수학점/졸업이수학점": "0.4801",
        "직전학기이수학점/학기당수강학점": "0.9166",
        "학년": "2",
        "수강여부": "X",
        "비고": ""
      },
      {
        "순위": "71",
        "마일리지": "1",
        "전공자/복수전공자": "N",
        "전공자정원포함여부": "N",
        "신청과목수": "6",
        "졸업신청": "N",
        "초수강여부": "Y",
        "총이수학점/졸업이수학점": "0.4444",
        "직전학기이수학점/학기당수강학점": "1.0000",
        "학년": "2",
        "수강여부": "X",
        "비고": ""
      },
      {
        "순위": "72",
        "마일리지": "1",
        "전공자/복수전공자": "N",
        "전공자정원포함여부": "N",
        "신청과목수": "6",
        "졸업신청": "N",
        "초수강여부": "Y",
        "총이수학점/졸업이수학점": "0.4285",
        "직전학기이수학점/학기당수강학점": "0.8611",
        "학년": "2",
        "수강여부": "X",
        "비고": ""
      },
      {
        "순위": "73",
        "마일리지": "1",
        "전공자/복수전공자": "N",
        "전공자정원포함여부": "N",
        "신청과목수": "6",
        "졸업신청": "N",
        "초수강여부": "Y",
        "총이수학점/졸업이수학점": "0.4126",
        "직전학기이수학점/학기당수강학점": "1.0000",
        "학년": "2",
        "수강여부": "X",
        "비고": ""
      },
      {
        "순위": "74",
        "마일리지": "1",
        "전공자/복수전공자": "N",
        "전공자정원포함여부": "N",
        "신청과목수": "6",
        "졸업신청": "N",
        "초수강여부": "Y",
        "총이수학점/졸업이수학점": "0.4071",
        "직전학기이수학점/학기당수강학점": "1.0000",
        "학년": "2",
        "수강여부": "X",
        "비고": ""
      },
      {
        "순위": "75",
        "마일리지": "1",
        "전공자/복수전공자": "N",
        "전공자정원포함여부": "N",
        "신청과목수": "6",
        "졸업신청": "N",
        "초수강여부": "Y",
        "총이수학점/졸업이수학점": "0.3750",
        "직전학기이수학점/학기당수강학점": "0.9210",
        "학년": "2",
        "수강여부": "X",
        "비고": ""
      },
      {
        "순위": "76",
        "마일리지": "1",
        "전공자/복수전공자": "N",
        "전공자정원포함여부": "N",
        "신청과목수": "6",
        "졸업신청": "N",
        "초수강여부": "Y",
        "총이수학점/졸업이수학점": "0.3481",
        "직전학기이수학점/학기당수강학점": "0.9473",
        "학년": "3",
        "수강여부": "O",
        "비고": ""
      }
    ]
  },
  "20202": {
    "CAUTION": {
      "필수교양(10~18학번)": {
        "가치와윤리": [
          "자세한 수업진행방식은 학부대학 홈페이지 정보마당 학생공지사항 참조",
          "100%온라인:동영상콘텐츠강의",
          "강의동영상제공",
          "절대평가"
        ]
      },
      "대학교양(2019학번~)": {
        "가치와윤리": [
          "자세한 수업진행방식은 학부대학 홈페이지 정보마당 학생공지사항 참조",
          "100%온라인:동영상콘텐츠강의",
          "강의동영상제공",
          "절대평가"
        ]
      }
    },
    "LECT_DATA": {
      "학정번호-분반-실습": "YCG1704-01-00",
      "과목명": "기독교와서구문명",
      "학점": "3",
      "담당교수": "윤혜준",
      "강의시간": "화8",
      "강의실": "동영상콘텐츠",
      "정원": "95",
      "참여인원": "184",
      "전공자정원": "0",
      "2전공포함": "N",
      "1학년정원": "0",
      "2학년정원": "32",
      "3학년정원": "31",
      "4학년정원": "32",
      "교환학생 가능여부": "O",
      "Max Mileage(limit)": "36",
      "Mileage_minimum": "1",
      "Mileage_maximum": "36",
      "Mileage_average": "17.81"
    },
    "RESULT_DATA": [
      {
        "순위": "1",
        "마일리지": "36",
        "전공자/복수전공자": "N",
        "전공자정원포함여부": "N",
        "신청과목수": "6",
        "졸업신청": "Y",
        "초수강여부": "Y",
        "총이수학점/졸업이수학점": "0.9185",
        "직전학기이수학점/학기당수강학점": "0.8421",
        "학년": "4",
        "수강여부": "O",
        "비고": ""
      },
      {
        "순위": "2",
        "마일리지": "36",
        "전공자/복수전공자": "N",
        "전공자정원포함여부": "N",
        "신청과목수": "6",
        "졸업신청": "Y",
        "초수강여부": "Y",
        "총이수학점/졸업이수학점": "0.9037",
        "직전학기이수학점/학기당수강학점": "0.7894",
        "학년": "4",
        "수강여부": "O",
        "비고": ""
      },
      {
        "순위": "3",
        "마일리지": "36",
        "전공자/복수전공자": "N",
        "전공자정원포함여부": "N",
        "신청과목수": "6",
        "졸업신청": "N",
        "초수강여부": "Y",
        "총이수학점/졸업이수학점": "0.9605",
        "직전학기이수학점/학기당수강학점": "0.9583",
        "학년": "2",
        "수강여부": "O",
        "비고": ""
      },
      {
        "순위": "4",
        "마일리지": "36",
        "전공자/복수전공자": "N",
        "전공자정원포함여부": "N",
        "신청과목수": "6",
        "졸업신청": "N",
        "초수강여부": "Y",
        "총이수학점/졸업이수학점": "0.8684",
        "직전학기이수학점/학기당수강학점": "0.8750",
        "학년": "2",
        "수강여부": "O",
        "비고": ""
      },
      {
        "순위": "5",
        "마일리지": "36",
        "전공자/복수전공자": "N",
        "전공자정원포함여부": "N",
        "신청과목수": "6",
        "졸업신청": "N",
        "초수강여부": "Y",
        "총이수학점/졸업이수학점": "0.8111",
        "직전학기이수학점/학기당수강학점": "0.8421",
        "학년": "4",
        "수강여부": "O",
        "비고": ""
      },
      {
        "순위": "6",
        "마일리지": "36",
        "전공자/복수전공자": "N",
        "전공자정원포함여부": "N",
        "신청과목수": "6",
        "졸업신청": "N",
        "초수강여부": "Y",
        "총이수학점/졸업이수학점": "0.7285",
        "직전학기이수학점/학기당수강학점": "1.0000",
        "학년": "3",
        "수강여부": "O",
        "비고": ""
      },
      {
        "순위": "7",
        "마일리지": "36",
        "전공자/복수전공자": "N",
        "전공자정원포함여부": "N",
        "신청과목수": "6",
        "졸업신청": "N",
        "초수강여부": "Y",
        "총이수학점/졸업이수학점": "0.6888",
        "직전학기이수학점/학기당수강학점": "1.0000",
        "학년": "3",
        "수강여부": "O",
        "비고": ""
      },
      {
        "순위": "8",
        "마일리지": "36",
        "전공자/복수전공자": "N",
        "전공자정원포함여부": "N",
        "신청과목수": "6",
        "졸업신청": "N",
        "초수강여부": "Y",
        "총이수학점/졸업이수학점": "0.6746",
        "직전학기이수학점/학기당수강학점": "1.0000",
        "학년": "3",
        "수강여부": "O",
        "비고": ""
      },
      {
        "순위": "9",
        "마일리지": "36",
        "전공자/복수전공자": "N",
        "전공자정원포함여부": "N",
        "신청과목수": "6",
        "졸업신청": "N",
        "초수강여부": "Y",
        "총이수학점/졸업이수학점": "0.6666",
        "직전학기이수학점/학기당수강학점": "1.0000",
        "학년": "3",
        "수강여부": "O",
        "비고": ""
      },
      {
        "순위": "10",
        "마일리지": "36",
        "전공자/복수전공자": "N",
        "전공자정원포함여부": "N",
        "신청과목수": "6",
        "졸업신청": "N",
        "초수강여부": "Y",
        "총이수학점/졸업이수학점": "0.6642",
        "직전학기이수학점/학기당수강학점": "1.0000",
        "학년": "3",
        "수강여부": "O",
        "비고": ""
      },
      {
        "순위": "11",
        "마일리지": "36",
        "전공자/복수전공자": "N",
        "전공자정원포함여부": "N",
        "신청과목수": "6",
        "졸업신청": "N",
        "초수강여부": "Y",
        "총이수학점/졸업이수학점": "0.6464",
        "직전학기이수학점/학기당수강학점": "1.0000",
        "학년": "3",
        "수강여부": "O",
        "비고": ""
      },
      {
        "순위": "12",
        "마일리지": "36",
        "전공자/복수전공자": "N",
        "전공자정원포함여부": "N",
        "신청과목수": "6",
        "졸업신청": "N",
        "초수강여부": "Y",
        "총이수학점/졸업이수학점": "0.6142",
        "직전학기이수학점/학기당수강학점": "1.0000",
        "학년": "3",
        "수강여부": "O",
        "비고": ""
      },
      {
        "순위": "13",
        "마일리지": "36",
        "전공자/복수전공자": "N",
        "전공자정원포함여부": "N",
        "신청과목수": "6",
        "졸업신청": "N",
        "초수강여부": "Y",
        "총이수학점/졸업이수학점": "0.5750",
        "직전학기이수학점/학기당수강학점": "1.0000",
        "학년": "3",
        "수강여부": "O",
        "비고": ""
      },
      {
        "순위": "14",
        "마일리지": "36",
        "전공자/복수전공자": "N",
        "전공자정원포함여부": "N",
        "신청과목수": "6",
        "졸업신청": "N",
        "초수강여부": "Y",
        "총이수학점/졸업이수학점": "0.5296",
        "직전학기이수학점/학기당수강학점": "1.0000",
        "학년": "3",
        "수강여부": "O",
        "비고": ""
      },
      {
        "순위": "15",
        "마일리지": "36",
        "전공자/복수전공자": "N",
        "전공자정원포함여부": "N",
        "신청과목수": "6",
        "졸업신청": "N",
        "초수강여부": "Y",
        "총이수학점/졸업이수학점": "0.5158",
        "직전학기이수학점/학기당수강학점": "0.8333",
        "학년": "3",
        "수강여부": "O",
        "비고": ""
      },
      {
        "순위": "16",
        "마일리지": "36",
        "전공자/복수전공자": "N",
        "전공자정원포함여부": "N",
        "신청과목수": "6",
        "졸업신청": "N",
        "초수강여부": "Y",
        "총이수학점/졸업이수학점": "0.4563",
        "직전학기이수학점/학기당수강학점": "1.0000",
        "학년": "2",
        "수강여부": "O",
        "비고": ""
      },
      {
        "순위": "17",
        "마일리지": "36",
        "전공자/복수전공자": "N",
        "전공자정원포함여부": "N",
        "신청과목수": "6",
        "졸업신청": "N",
        "초수강여부": "Y",
        "총이수학점/졸업이수학점": "0.4563",
        "직전학기이수학점/학기당수강학점": "0.8611",
        "학년": "2",
        "수강여부": "O",
        "비고": ""
      },
      {
        "순위": "18",
        "마일리지": "36",
        "전공자/복수전공자": "N",
        "전공자정원포함여부": "N",
        "신청과목수": "6",
        "졸업신청": "N",
        "초수강여부": "Y",
        "총이수학점/졸업이수학점": "0.4333",
        "직전학기이수학점/학기당수강학점": "1.0000",
        "학년": "2",
        "수강여부": "O",
        "비고": ""
      },
      {
        "순위": "19",
        "마일리지": "36",
        "전공자/복수전공자": "N",
        "전공자정원포함여부": "N",
        "신청과목수": "6",
        "졸업신청": "N",
        "초수강여부": "Y",
        "총이수학점/졸업이수학점": "0.4259",
        "직전학기이수학점/학기당수강학점": "1.0000",
        "학년": "2",
        "수강여부": "O",
        "비고": ""
      },
      {
        "순위": "20",
        "마일리지": "36",
        "전공자/복수전공자": "N",
        "전공자정원포함여부": "N",
        "신청과목수": "6",
        "졸업신청": "N",
        "초수강여부": "Y",
        "총이수학점/졸업이수학점": "0.4087",
        "직전학기이수학점/학기당수강학점": "0.8611",
        "학년": "2",
        "수강여부": "O",
        "비고": ""
      },
      {
        "순위": "21",
        "마일리지": "36",
        "전공자/복수전공자": "N",
        "전공자정원포함여부": "N",
        "신청과목수": "6",
        "졸업신청": "N",
        "초수강여부": "Y",
        "총이수학점/졸업이수학점": "0.4087",
        "직전학기이수학점/학기당수강학점": "0.8611",
        "학년": "2",
        "수강여부": "O",
        "비고": ""
      },
      {
        "순위": "22",
        "마일리지": "36",
        "전공자/복수전공자": "N",
        "전공자정원포함여부": "N",
        "신청과목수": "6",
        "졸업신청": "N",
        "초수강여부": "Y",
        "총이수학점/졸업이수학점": "0.4087",
        "직전학기이수학점/학기당수강학점": "0.8333",
        "학년": "2",
        "수강여부": "O",
        "비고": ""
      },
      {
        "순위": "23",
        "마일리지": "36",
        "전공자/복수전공자": "N",
        "전공자정원포함여부": "N",
        "신청과목수": "6",
        "졸업신청": "N",
        "초수강여부": "Y",
        "총이수학점/졸업이수학점": "0.4037",
        "직전학기이수학점/학기당수강학점": "0.9736",
        "학년": "2",
        "수강여부": "O",
        "비고": ""
      },
      {
        "순위": "24",
        "마일리지": "36",
        "전공자/복수전공자": "N",
        "전공자정원포함여부": "N",
        "신청과목수": "6",
        "졸업신청": "N",
        "초수강여부": "Y",
        "총이수학점/졸업이수학점": "0.4007",
        "직전학기이수학점/학기당수강학점": "0.8611",
        "학년": "2",
        "수강여부": "O",
        "비고": ""
      },
      {
        "순위": "25",
        "마일리지": "36",
        "전공자/복수전공자": "N",
        "전공자정원포함여부": "N",
        "신청과목수": "6",
        "졸업신청": "N",
        "초수강여부": "Y",
        "총이수학점/졸업이수학점": "0.3925",
        "직전학기이수학점/학기당수강학점": "0.9473",
        "학년": "2",
        "수강여부": "O",
        "비고": ""
      },
      {
        "순위": "26",
        "마일리지": "36",
        "전공자/복수전공자": "N",
        "전공자정원포함여부": "N",
        "신청과목수": "6",
        "졸업신청": "N",
        "초수강여부": "Y",
        "총이수학점/졸업이수학점": "0.3849",
        "직전학기이수학점/학기당수강학점": "1.0000",
        "학년": "2",
        "수강여부": "O",
        "비고": ""
      },
      {
        "순위": "27",
        "마일리지": "36",
        "전공자/복수전공자": "N",
        "전공자정원포함여부": "N",
        "신청과목수": "6",
        "졸업신청": "N",
        "초수강여부": "Y",
        "총이수학점/졸업이수학점": "0.3185",
        "직전학기이수학점/학기당수강학점": "0.8157",
        "학년": "2",
        "수강여부": "O",
        "비고": ""
      },
      {
        "순위": "28",
        "마일리지": "36",
        "전공자/복수전공자": "N",
        "전공자정원포함여부": "N",
        "신청과목수": "5",
        "졸업신청": "Y",
        "초수강여부": "Y",
        "총이수학점/졸업이수학점": "0.9142",
        "직전학기이수학점/학기당수강학점": "0.7894",
        "학년": "4",
        "수강여부": "O",
        "비고": ""
      },
      {
        "순위": "29",
        "마일리지": "36",
        "전공자/복수전공자": "N",
        "전공자정원포함여부": "N",
        "신청과목수": "3",
        "졸업신청": "Y",
        "초수강여부": "Y",
        "총이수학점/졸업이수학점": "1.0000",
        "직전학기이수학점/학기당수강학점": "0.9444",
        "학년": "4",
        "수강여부": "O",
        "비고": ""
      },
      {
        "순위": "30",
        "마일리지": "35",
        "전공자/복수전공자": "N",
        "전공자정원포함여부": "N",
        "신청과목수": "6",
        "졸업신청": "N",
        "초수강여부": "Y",
        "총이수학점/졸업이수학점": "0.3740",
        "직전학기이수학점/학기당수강학점": "0.8684",
        "학년": "2",
        "수강여부": "O",
        "비고": ""
      },
      {
        "순위": "31",
        "마일리지": "34",
        "전공자/복수전공자": "N",
        "전공자정원포함여부": "N",
        "신청과목수": "6",
        "졸업신청": "N",
        "초수강여부": "Y",
        "총이수학점/졸업이수학점": "0.6642",
        "직전학기이수학점/학기당수강학점": "0.9473",
        "학년": "3",
        "수강여부": "O",
        "비고": ""
      },
      {
        "순위": "32",
        "마일리지": "34",
        "전공자/복수전공자": "N",
        "전공자정원포함여부": "N",
        "신청과목수": "6",
        "졸업신청": "N",
        "초수강여부": "Y",
        "총이수학점/졸업이수학점": "0.6500",
        "직전학기이수학점/학기당수강학점": "0.8947",
        "학년": "3",
        "수강여부": "O",
        "비고": ""
      },
      {
        "순위": "33",
        "마일리지": "33",
        "전공자/복수전공자": "N",
        "전공자정원포함여부": "N",
        "신청과목수": "6",
        "졸업신청": "N",
        "초수강여부": "Y",
        "총이수학점/졸업이수학점": "0.4939",
        "직전학기이수학점/학기당수강학점": "0.8157",
        "학년": "3",
        "수강여부": "O",
        "비고": ""
      },
      {
        "순위": "34",
        "마일리지": "32",
        "전공자/복수전공자": "N",
        "전공자정원포함여부": "N",
        "신청과목수": "6",
        "졸업신청": "N",
        "초수강여부": "Y",
        "총이수학점/졸업이수학점": "0.4563",
        "직전학기이수학점/학기당수강학점": "1.0000",
        "학년": "2",
        "수강여부": "O",
        "비고": ""
      },
      {
        "순위": "35",
        "마일리지": "32",
        "전공자/복수전공자": "N",
        "전공자정원포함여부": "N",
        "신청과목수": "6",
        "졸업신청": "N",
        "초수강여부": "Y",
        "총이수학점/졸업이수학점": "0.4296",
        "직전학기이수학점/학기당수강학점": "0.7631",
        "학년": "3",
        "수강여부": "O",
        "비고": ""
      },
      {
        "순위": "36",
        "마일리지": "30",
        "전공자/복수전공자": "N",
        "전공자정원포함여부": "N",
        "신청과목수": "6",
        "졸업신청": "N",
        "초수강여부": "Y",
        "총이수학점/졸업이수학점": "0.9703",
        "직전학기이수학점/학기당수강학점": "0.9473",
        "학년": "4",
        "수강여부": "O",
        "비고": ""
      },
      {
        "순위": "37",
        "마일리지": "30",
        "전공자/복수전공자": "N",
        "전공자정원포함여부": "N",
        "신청과목수": "6",
        "졸업신청": "N",
        "초수강여부": "Y",
        "총이수학점/졸업이수학점": "0.6857",
        "직전학기이수학점/학기당수강학점": "0.9473",
        "학년": "3",
        "수강여부": "O",
        "비고": ""
      },
      {
        "순위": "38",
        "마일리지": "30",
        "전공자/복수전공자": "N",
        "전공자정원포함여부": "N",
        "신청과목수": "6",
        "졸업신청": "N",
        "초수강여부": "Y",
        "총이수학점/졸업이수학점": "0.6428",
        "직전학기이수학점/학기당수강학점": "0.9736",
        "학년": "3",
        "수강여부": "O",
        "비고": ""
      },
      {
        "순위": "39",
        "마일리지": "30",
        "전공자/복수전공자": "N",
        "전공자정원포함여부": "N",
        "신청과목수": "6",
        "졸업신청": "N",
        "초수강여부": "Y",
        "총이수학점/졸업이수학점": "0.3111",
        "직전학기이수학점/학기당수강학점": "1.0000",
        "학년": "2",
        "수강여부": "O",
        "비고": ""
      },
      {
        "순위": "40",
        "마일리지": "29",
        "전공자/복수전공자": "N",
        "전공자정원포함여부": "N",
        "신청과목수": "6",
        "졸업신청": "N",
        "초수강여부": "Y",
        "총이수학점/졸업이수학점": "0.4246",
        "직전학기이수학점/학기당수강학점": "0.9166",
        "학년": "2",
        "수강여부": "O",
        "비고": ""
      },
      {
        "순위": "41",
        "마일리지": "29",
        "전공자/복수전공자": "N",
        "전공자정원포함여부": "N",
        "신청과목수": "6",
        "졸업신청": "N",
        "초수강여부": "Y",
        "총이수학점/졸업이수학점": "0.4047",
        "직전학기이수학점/학기당수강학점": "0.8333",
        "학년": "2",
        "수강여부": "O",
        "비고": ""
      },
      {
        "순위": "42",
        "마일리지": "28",
        "전공자/복수전공자": "N",
        "전공자정원포함여부": "N",
        "신청과목수": "6",
        "졸업신청": "Y",
        "초수강여부": "Y",
        "총이수학점/졸업이수학점": "0.9206",
        "직전학기이수학점/학기당수강학점": "0.8888",
        "학년": "4",
        "수강여부": "O",
        "비고": ""
      },
      {
        "순위": "43",
        "마일리지": "27",
        "전공자/복수전공자": "N",
        "전공자정원포함여부": "N",
        "신청과목수": "6",
        "졸업신청": "Y",
        "초수강여부": "Y",
        "총이수학점/졸업이수학점": "0.8928",
        "직전학기이수학점/학기당수강학점": "1.0000",
        "학년": "4",
        "수강여부": "O",
        "비고": ""
      },
      {
        "순위": "44",
        "마일리지": "27",
        "전공자/복수전공자": "N",
        "전공자정원포함여부": "N",
        "신청과목수": "6",
        "졸업신청": "N",
        "초수강여부": "Y",
        "총이수학점/졸업이수학점": "0.4206",
        "직전학기이수학점/학기당수강학점": "1.0000",
        "학년": "2",
        "수강여부": "O",
        "비고": ""
      },
      {
        "순위": "45",
        "마일리지": "27",
        "전공자/복수전공자": "N",
        "전공자정원포함여부": "N",
        "신청과목수": "6",
        "졸업신청": "N",
        "초수강여부": "Y",
        "총이수학점/졸업이수학점": "0.3214",
        "직전학기이수학점/학기당수강학점": "0.8611",
        "학년": "2",
        "수강여부": "O",
        "비고": ""
      },
      {
        "순위": "46",
        "마일리지": "26",
        "전공자/복수전공자": "N",
        "전공자정원포함여부": "N",
        "신청과목수": "6",
        "졸업신청": "N",
        "초수강여부": "Y",
        "총이수학점/졸업이수학점": "0.4703",
        "직전학기이수학점/학기당수강학점": "0.9736",
        "학년": "2",
        "수강여부": "O",
        "비고": ""
      },
      {
        "순위": "47",
        "마일리지": "25",
        "전공자/복수전공자": "N",
        "전공자정원포함여부": "N",
        "신청과목수": "6",
        "졸업신청": "Y",
        "초수강여부": "Y",
        "총이수학점/졸업이수학점": "0.9285",
        "직전학기이수학점/학기당수강학점": "1.0000",
        "학년": "4",
        "수강여부": "O",
        "비고": ""
      },
      {
        "순위": "48",
        "마일리지": "25",
        "전공자/복수전공자": "N",
        "전공자정원포함여부": "N",
        "신청과목수": "6",
        "졸업신청": "N",
        "초수강여부": "Y",
        "총이수학점/졸업이수학점": "0.7777",
        "직전학기이수학점/학기당수강학점": "1.0000",
        "학년": "4",
        "수강여부": "O",
        "비고": ""
      },
      {
        "순위": "49",
        "마일리지": "25",
        "전공자/복수전공자": "N",
        "전공자정원포함여부": "N",
        "신청과목수": "6",
        "졸업신청": "N",
        "초수강여부": "Y",
        "총이수학점/졸업이수학점": "0.7301",
        "직전학기이수학점/학기당수강학점": "1.0000",
        "학년": "4",
        "수강여부": "O",
        "비고": ""
      },
      {
        "순위": "50",
        "마일리지": "25",
        "전공자/복수전공자": "N",
        "전공자정원포함여부": "N",
        "신청과목수": "6",
        "졸업신청": "N",
        "초수강여부": "Y",
        "총이수학점/졸업이수학점": "0.6555",
        "직전학기이수학점/학기당수강학점": "1.0000",
        "학년": "3",
        "수강여부": "O",
        "비고": ""
      },
      {
        "순위": "51",
        "마일리지": "24",
        "전공자/복수전공자": "N",
        "전공자정원포함여부": "N",
        "신청과목수": "6",
        "졸업신청": "N",
        "초수강여부": "Y",
        "총이수학점/졸업이수학점": "0.6714",
        "직전학기이수학점/학기당수강학점": "0.7894",
        "학년": "3",
        "수강여부": "O",
        "비고": ""
      },
      {
        "순위": "52",
        "마일리지": "24",
        "전공자/복수전공자": "N",
        "전공자정원포함여부": "N",
        "신청과목수": "6",
        "졸업신청": "N",
        "초수강여부": "Y",
        "총이수학점/졸업이수학점": "0.5301",
        "직전학기이수학점/학기당수강학점": "0.9473",
        "학년": "3",
        "수강여부": "O",
        "비고": ""
      },
      {
        "순위": "53",
        "마일리지": "24",
        "전공자/복수전공자": "N",
        "전공자정원포함여부": "N",
        "신청과목수": "6",
        "졸업신청": "N",
        "초수강여부": "Y",
        "총이수학점/졸업이수학점": "0.5271",
        "직전학기이수학점/학기당수강학점": "0.9736",
        "학년": "3",
        "수강여부": "O",
        "비고": ""
      },
      {
        "순위": "54",
        "마일리지": "24",
        "전공자/복수전공자": "N",
        "전공자정원포함여부": "N",
        "신청과목수": "6",
        "졸업신청": "N",
        "초수강여부": "Y",
        "총이수학점/졸업이수학점": "0.3962",
        "직전학기이수학점/학기당수강학점": "0.9736",
        "학년": "2",
        "수강여부": "O",
        "비고": ""
      },
      {
        "순위": "55",
        "마일리지": "23",
        "전공자/복수전공자": "N",
        "전공자정원포함여부": "N",
        "신청과목수": "6",
        "졸업신청": "Y",
        "초수강여부": "Y",
        "총이수학점/졸업이수학점": "0.9047",
        "직전학기이수학점/학기당수강학점": "1.0000",
        "학년": "4",
        "수강여부": "O",
        "비고": ""
      },
      {
        "순위": "56",
        "마일리지": "23",
        "전공자/복수전공자": "N",
        "전공자정원포함여부": "N",
        "신청과목수": "6",
        "졸업신청": "N",
        "초수강여부": "Y",
        "총이수학점/졸업이수학점": "0.7698",
        "직전학기이수학점/학기당수강학점": "0.9444",
        "학년": "4",
        "수강여부": "O",
        "비고": ""
      },
      {
        "순위": "57",
        "마일리지": "23",
        "전공자/복수전공자": "N",
        "전공자정원포함여부": "N",
        "신청과목수": "6",
        "졸업신청": "N",
        "초수강여부": "Y",
        "총이수학점/졸업이수학점": "0.6984",
        "직전학기이수학점/학기당수강학점": "1.0000",
        "학년": "3",
        "수강여부": "O",
        "비고": ""
      },
      {
        "순위": "58",
        "마일리지": "23",
        "전공자/복수전공자": "N",
        "전공자정원포함여부": "N",
        "신청과목수": "6",
        "졸업신청": "N",
        "초수강여부": "Y",
        "총이수학점/졸업이수학점": "0.6825",
        "직전학기이수학점/학기당수강학점": "1.0000",
        "학년": "3",
        "수강여부": "O",
        "비고": ""
      },
      {
        "순위": "59",
        "마일리지": "23",
        "전공자/복수전공자": "N",
        "전공자정원포함여부": "N",
        "신청과목수": "6",
        "졸업신청": "N",
        "초수강여부": "Y",
        "총이수학점/졸업이수학점": "0.6333",
        "직전학기이수학점/학기당수강학점": "0.7894",
        "학년": "3",
        "수강여부": "O",
        "비고": ""
      },
      {
        "순위": "60",
        "마일리지": "23",
        "전공자/복수전공자": "N",
        "전공자정원포함여부": "N",
        "신청과목수": "6",
        "졸업신청": "N",
        "초수강여부": "Y",
        "총이수학점/졸업이수학점": "0.4789",
        "직전학기이수학점/학기당수강학점": "0.9736",
        "학년": "3",
        "수강여부": "O",
        "비고": ""
      },
      {
        "순위": "61",
        "마일리지": "23",
        "전공자/복수전공자": "N",
        "전공자정원포함여부": "N",
        "신청과목수": "6",
        "졸업신청": "N",
        "초수강여부": "Y",
        "총이수학점/졸업이수학점": "0.4484",
        "직전학기이수학점/학기당수강학점": "1.0000",
        "학년": "2",
        "수강여부": "O",
        "비고": ""
      },
      {
        "순위": "62",
        "마일리지": "23",
        "전공자/복수전공자": "N",
        "전공자정원포함여부": "N",
        "신청과목수": "5",
        "졸업신청": "N",
        "초수강여부": "Y",
        "총이수학점/졸업이수학점": "0.8412",
        "직전학기이수학점/학기당수강학점": "0.9285",
        "학년": "4",
        "수강여부": "O",
        "비고": ""
      },
      {
        "순위": "63",
        "마일리지": "22",
        "전공자/복수전공자": "N",
        "전공자정원포함여부": "N",
        "신청과목수": "6",
        "졸업신청": "N",
        "초수강여부": "Y",
        "총이수학점/졸업이수학점": "0.4325",
        "직전학기이수학점/학기당수강학점": "1.0000",
        "학년": "2",
        "수강여부": "O",
        "비고": ""
      },
      {
        "순위": "64",
        "마일리지": "22",
        "전공자/복수전공자": "N",
        "전공자정원포함여부": "N",
        "신청과목수": "6",
        "졸업신청": "N",
        "초수강여부": "Y",
        "총이수학점/졸업이수학점": "0.4166",
        "직전학기이수학점/학기당수강학점": "1.0000",
        "학년": "2",
        "수강여부": "O",
        "비고": ""
      },
      {
        "순위": "65",
        "마일리지": "22",
        "전공자/복수전공자": "N",
        "전공자정원포함여부": "N",
        "신청과목수": "6",
        "졸업신청": "N",
        "초수강여부": "Y",
        "총이수학점/졸업이수학점": "0.4087",
        "직전학기이수학점/학기당수강학점": "0.8611",
        "학년": "2",
        "수강여부": "O",
        "비고": ""
      },
      {
        "순위": "66",
        "마일리지": "22",
        "전공자/복수전공자": "N",
        "전공자정원포함여부": "N",
        "신청과목수": "6",
        "졸업신청": "N",
        "초수강여부": "Y",
        "총이수학점/졸업이수학점": "0.3968",
        "직전학기이수학점/학기당수강학점": "0.9722",
        "학년": "2",
        "수강여부": "O",
        "비고": ""
      },
      {
        "순위": "67",
        "마일리지": "22",
        "전공자/복수전공자": "N",
        "전공자정원포함여부": "N",
        "신청과목수": "6",
        "졸업신청": "N",
        "초수강여부": "Y",
        "총이수학점/졸업이수학점": "0.3293",
        "직전학기이수학점/학기당수강학점": "0.6666",
        "학년": "2",
        "수강여부": "O",
        "비고": ""
      },
      {
        "순위": "68",
        "마일리지": "22",
        "전공자/복수전공자": "N",
        "전공자정원포함여부": "N",
        "신청과목수": "6",
        "졸업신청": "N",
        "초수강여부": "Y",
        "총이수학점/졸업이수학점": "0.3174",
        "직전학기이수학점/학기당수강학점": "0.6944",
        "학년": "2",
        "수강여부": "O",
        "비고": ""
      },
      {
        "순위": "69",
        "마일리지": "21",
        "전공자/복수전공자": "N",
        "전공자정원포함여부": "N",
        "신청과목수": "6",
        "졸업신청": "N",
        "초수강여부": "Y",
        "총이수학점/졸업이수학점": "0.8571",
        "직전학기이수학점/학기당수강학점": "0.8333",
        "학년": "4",
        "수강여부": "O",
        "비고": ""
      },
      {
        "순위": "70",
        "마일리지": "21",
        "전공자/복수전공자": "N",
        "전공자정원포함여부": "N",
        "신청과목수": "6",
        "졸업신청": "N",
        "초수강여부": "Y",
        "총이수학점/졸업이수학점": "0.7281",
        "직전학기이수학점/학기당수강학점": "1.0000",
        "학년": "3",
        "수강여부": "O",
        "비고": ""
      },
      {
        "순위": "71",
        "마일리지": "21",
        "전공자/복수전공자": "N",
        "전공자정원포함여부": "N",
        "신청과목수": "6",
        "졸업신청": "N",
        "초수강여부": "Y",
        "총이수학점/졸업이수학점": "0.4321",
        "직전학기이수학점/학기당수강학점": "0.9736",
        "학년": "2",
        "수강여부": "O",
        "비고": ""
      },
      {
        "순위": "72",
        "마일리지": "21",
        "전공자/복수전공자": "N",
        "전공자정원포함여부": "N",
        "신청과목수": "6",
        "졸업신청": "N",
        "초수강여부": "Y",
        "총이수학점/졸업이수학점": "0.4047",
        "직전학기이수학점/학기당수강학점": "1.0000",
        "학년": "2",
        "수강여부": "O",
        "비고": ""
      },
      {
        "순위": "73",
        "마일리지": "21",
        "전공자/복수전공자": "N",
        "전공자정원포함여부": "N",
        "신청과목수": "6",
        "졸업신청": "N",
        "초수강여부": "Y",
        "총이수학점/졸업이수학점": "0.4037",
        "직전학기이수학점/학기당수강학점": "0.8157",
        "학년": "2",
        "수강여부": "X",
        "비고": ""
      },
      {
        "순위": "74",
        "마일리지": "21",
        "전공자/복수전공자": "N",
        "전공자정원포함여부": "N",
        "신청과목수": "6",
        "졸업신청": "N",
        "초수강여부": "Y",
        "총이수학점/졸업이수학점": "0.3250",
        "직전학기이수학점/학기당수강학점": "0.9736",
        "학년": "2",
        "수강여부": "X",
        "비고": ""
      },
      {
        "순위": "75",
        "마일리지": "20",
        "전공자/복수전공자": "N",
        "전공자정원포함여부": "N",
        "신청과목수": "6",
        "졸업신청": "N",
        "초수강여부": "Y",
        "총이수학점/졸업이수학점": "0.7063",
        "직전학기이수학점/학기당수강학점": "0.8055",
        "학년": "4",
        "수강여부": "O",
        "비고": ""
      },
      {
        "순위": "76",
        "마일리지": "20",
        "전공자/복수전공자": "N",
        "전공자정원포함여부": "N",
        "신청과목수": "6",
        "졸업신청": "N",
        "초수강여부": "Y",
        "총이수학점/졸업이수학점": "0.5060",
        "직전학기이수학점/학기당수강학점": "0.9736",
        "학년": "3",
        "수강여부": "O",
        "비고": ""
      },
      {
        "순위": "77",
        "마일리지": "20",
        "전공자/복수전공자": "N",
        "전공자정원포함여부": "N",
        "신청과목수": "6",
        "졸업신청": "N",
        "초수강여부": "Y",
        "총이수학점/졸업이수학점": "0.4087",
        "직전학기이수학점/학기당수강학점": "0.8611",
        "학년": "2",
        "수강여부": "X",
        "비고": ""
      },
      {
        "순위": "78",
        "마일리지": "20",
        "전공자/복수전공자": "N",
        "전공자정원포함여부": "N",
        "신청과목수": "6",
        "졸업신청": "N",
        "초수강여부": "Y",
        "총이수학점/졸업이수학점": "0.4047",
        "직전학기이수학점/학기당수강학점": "0.8611",
        "학년": "2",
        "수강여부": "X",
        "비고": ""
      },
      {
        "순위": "79",
        "마일리지": "20",
        "전공자/복수전공자": "N",
        "전공자정원포함여부": "N",
        "신청과목수": "6",
        "졸업신청": "N",
        "초수강여부": "Y",
        "총이수학점/졸업이수학점": "0.3650",
        "직전학기이수학점/학기당수강학점": "1.0000",
        "학년": "2",
        "수강여부": "X",
        "비고": ""
      },
      {
        "순위": "80",
        "마일리지": "20",
        "전공자/복수전공자": "N",
        "전공자정원포함여부": "N",
        "신청과목수": "6",
        "졸업신청": "N",
        "초수강여부": "Y",
        "총이수학점/졸업이수학점": "0.3296",
        "직전학기이수학점/학기당수강학점": "0.9736",
        "학년": "2",
        "수강여부": "X",
        "비고": ""
      },
      {
        "순위": "81",
        "마일리지": "20",
        "전공자/복수전공자": "N",
        "전공자정원포함여부": "N",
        "신청과목수": "6",
        "졸업신청": "N",
        "초수강여부": "Y",
        "총이수학점/졸업이수학점": "0.3253",
        "직전학기이수학점/학기당수강학점": "1.0000",
        "학년": "2",
        "수강여부": "X",
        "비고": ""
      },
      {
        "순위": "82",
        "마일리지": "19",
        "전공자/복수전공자": "N",
        "전공자정원포함여부": "N",
        "신청과목수": "6",
        "졸업신청": "N",
        "초수강여부": "Y",
        "총이수학점/졸업이수학점": "0.7698",
        "직전학기이수학점/학기당수강학점": "0.9722",
        "학년": "3",
        "수강여부": "O",
        "비고": ""
      },
      {
        "순위": "83",
        "마일리지": "19",
        "전공자/복수전공자": "N",
        "전공자정원포함여부": "N",
        "신청과목수": "6",
        "졸업신청": "N",
        "초수강여부": "Y",
        "총이수학점/졸업이수학점": "0.5119",
        "직전학기이수학점/학기당수강학점": "0.8611",
        "학년": "3",
        "수강여부": "O",
        "비고": ""
      },
      {
        "순위": "84",
        "마일리지": "19",
        "전공자/복수전공자": "N",
        "전공자정원포함여부": "N",
        "신청과목수": "6",
        "졸업신청": "N",
        "초수강여부": "Y",
        "총이수학점/졸업이수학점": "0.4801",
        "직전학기이수학점/학기당수강학점": "1.0000",
        "학년": "2",
        "수강여부": "X",
        "비고": ""
      },
      {
        "순위": "85",
        "마일리지": "19",
        "전공자/복수전공자": "N",
        "전공자정원포함여부": "N",
        "신청과목수": "6",
        "졸업신청": "N",
        "초수강여부": "Y",
        "총이수학점/졸업이수학점": "0.4071",
        "직전학기이수학점/학기당수강학점": "0.9473",
        "학년": "2",
        "수강여부": "X",
        "비고": ""
      },
      {
        "순위": "86",
        "마일리지": "18",
        "전공자/복수전공자": "N",
        "전공자정원포함여부": "N",
        "신청과목수": "6",
        "졸업신청": "Y",
        "초수강여부": "Y",
        "총이수학점/졸업이수학점": "0.8642",
        "직전학기이수학점/학기당수강학점": "0.9473",
        "학년": "4",
        "수강여부": "O",
        "비고": ""
      },
      {
        "순위": "87",
        "마일리지": "18",
        "전공자/복수전공자": "N",
        "전공자정원포함여부": "N",
        "신청과목수": "6",
        "졸업신청": "N",
        "초수강여부": "Y",
        "총이수학점/졸업이수학점": "0.7460",
        "직전학기이수학점/학기당수강학점": "0.8888",
        "학년": "3",
        "수강여부": "O",
        "비고": ""
      },
      {
        "순위": "88",
        "마일리지": "18",
        "전공자/복수전공자": "N",
        "전공자정원포함여부": "N",
        "신청과목수": "6",
        "졸업신청": "N",
        "초수강여부": "Y",
        "총이수학점/졸업이수학점": "0.6464",
        "직전학기이수학점/학기당수강학점": "0.9736",
        "학년": "3",
        "수강여부": "O",
        "비고": ""
      },
      {
        "순위": "89",
        "마일리지": "18",
        "전공자/복수전공자": "N",
        "전공자정원포함여부": "N",
        "신청과목수": "6",
        "졸업신청": "N",
        "초수강여부": "Y",
        "총이수학점/졸업이수학점": "0.4107",
        "직전학기이수학점/학기당수강학점": "0.9736",
        "학년": "2",
        "수강여부": "X",
        "비고": ""
      },
      {
        "순위": "90",
        "마일리지": "18",
        "전공자/복수전공자": "N",
        "전공자정원포함여부": "N",
        "신청과목수": "4",
        "졸업신청": "Y",
        "초수강여부": "Y",
        "총이수학점/졸업이수학점": "0.8857",
        "직전학기이수학점/학기당수강학점": "0.7894",
        "학년": "4",
        "수강여부": "O",
        "비고": ""
      },
      {
        "순위": "91",
        "마일리지": "17",
        "전공자/복수전공자": "N",
        "전공자정원포함여부": "N",
        "신청과목수": "6",
        "졸업신청": "N",
        "초수강여부": "Y",
        "총이수학점/졸업이수학점": "0.5595",
        "직전학기이수학점/학기당수강학점": "0.8611",
        "학년": "3",
        "수강여부": "O",
        "비고": ""
      },
      {
        "순위": "92",
        "마일리지": "17",
        "전공자/복수전공자": "N",
        "전공자정원포함여부": "N",
        "신청과목수": "6",
        "졸업신청": "N",
        "초수강여부": "Y",
        "총이수학점/졸업이수학점": "0.5407",
        "직전학기이수학점/학기당수강학점": "0.9736",
        "학년": "3",
        "수강여부": "X",
        "비고": ""
      },
      {
        "순위": "93",
        "마일리지": "16",
        "전공자/복수전공자": "N",
        "전공자정원포함여부": "N",
        "신청과목수": "6",
        "졸업신청": "N",
        "초수강여부": "Y",
        "총이수학점/졸업이수학점": "0.7777",
        "직전학기이수학점/학기당수강학점": "0.5555",
        "학년": "4",
        "수강여부": "O",
        "비고": ""
      },
      {
        "순위": "94",
        "마일리지": "16",
        "전공자/복수전공자": "N",
        "전공자정원포함여부": "N",
        "신청과목수": "5",
        "졸업신청": "N",
        "초수강여부": "Y",
        "총이수학점/졸업이수학점": "0.2658",
        "직전학기이수학점/학기당수강학점": "0.9166",
        "학년": "2",
        "수강여부": "X",
        "비고": ""
      },
      {
        "순위": "95",
        "마일리지": "15",
        "전공자/복수전공자": "N",
        "전공자정원포함여부": "N",
        "신청과목수": "6",
        "졸업신청": "N",
        "초수강여부": "Y",
        "총이수학점/졸업이수학점": "0.6407",
        "직전학기이수학점/학기당수강학점": "0.9736",
        "학년": "3",
        "수강여부": "X",
        "비고": ""
      },
      {
        "순위": "96",
        "마일리지": "15",
        "전공자/복수전공자": "N",
        "전공자정원포함여부": "N",
        "신청과목수": "6",
        "졸업신청": "N",
        "초수강여부": "Y",
        "총이수학점/졸업이수학점": "0.3925",
        "직전학기이수학점/학기당수강학점": "0.9736",
        "학년": "2",
        "수강여부": "X",
        "비고": ""
      },
      {
        "순위": "97",
        "마일리지": "15",
        "전공자/복수전공자": "N",
        "전공자정원포함여부": "N",
        "신청과목수": "4",
        "졸업신청": "Y",
        "초수강여부": "Y",
        "총이수학점/졸업이수학점": "0.9444",
        "직전학기이수학점/학기당수강학점": "1.0000",
        "학년": "4",
        "수강여부": "O",
        "비고": ""
      },
      {
        "순위": "98",
        "마일리지": "14",
        "전공자/복수전공자": "N",
        "전공자정원포함여부": "N",
        "신청과목수": "6",
        "졸업신청": "Y",
        "초수강여부": "Y",
        "총이수학점/졸업이수학점": "0.9142",
        "직전학기이수학점/학기당수강학점": "0.6315",
        "학년": "4",
        "수강여부": "O",
        "비고": ""
      },
      {
        "순위": "99",
        "마일리지": "14",
        "전공자/복수전공자": "N",
        "전공자정원포함여부": "N",
        "신청과목수": "6",
        "졸업신청": "Y",
        "초수강여부": "Y",
        "총이수학점/졸업이수학점": "0.8714",
        "직전학기이수학점/학기당수강학점": "0.7894",
        "학년": "4",
        "수강여부": "O",
        "비고": ""
      },
      {
        "순위": "100",
        "마일리지": "14",
        "전공자/복수전공자": "N",
        "전공자정원포함여부": "N",
        "신청과목수": "6",
        "졸업신청": "Y",
        "초수강여부": "Y",
        "총이수학점/졸업이수학점": "0.8592",
        "직전학기이수학점/학기당수강학점": "0.7894",
        "학년": "4",
        "수강여부": "O",
        "비고": ""
      },
      {
        "순위": "101",
        "마일리지": "14",
        "전공자/복수전공자": "N",
        "전공자정원포함여부": "N",
        "신청과목수": "6",
        "졸업신청": "N",
        "초수강여부": "Y",
        "총이수학점/졸업이수학점": "0.8154",
        "직전학기이수학점/학기당수강학점": "1.0000",
        "학년": "4",
        "수강여부": "O",
        "비고": ""
      },
      {
        "순위": "102",
        "마일리지": "14",
        "전공자/복수전공자": "N",
        "전공자정원포함여부": "N",
        "신청과목수": "6",
        "졸업신청": "N",
        "초수강여부": "Y",
        "총이수학점/졸업이수학점": "0.6642",
        "직전학기이수학점/학기당수강학점": "0.9473",
        "학년": "3",
        "수강여부": "X",
        "비고": ""
      },
      {
        "순위": "103",
        "마일리지": "14",
        "전공자/복수전공자": "N",
        "전공자정원포함여부": "N",
        "신청과목수": "6",
        "졸업신청": "N",
        "초수강여부": "Y",
        "총이수학점/졸업이수학점": "0.6000",
        "직전학기이수학점/학기당수강학점": "0.9473",
        "학년": "3",
        "수강여부": "X",
        "비고": ""
      },
      {
        "순위": "104",
        "마일리지": "14",
        "전공자/복수전공자": "N",
        "전공자정원포함여부": "N",
        "신청과목수": "6",
        "졸업신청": "N",
        "초수강여부": "Y",
        "총이수학점/졸업이수학점": "0.4563",
        "직전학기이수학점/학기당수강학점": "1.0000",
        "학년": "2",
        "수강여부": "X",
        "비고": ""
      },
      {
        "순위": "105",
        "마일리지": "14",
        "전공자/복수전공자": "N",
        "전공자정원포함여부": "N",
        "신청과목수": "6",
        "졸업신청": "N",
        "초수강여부": "Y",
        "총이수학점/졸업이수학점": "0.4563",
        "직전학기이수학점/학기당수강학점": "0.9166",
        "학년": "2",
        "수강여부": "X",
        "비고": ""
      },
      {
        "순위": "106",
        "마일리지": "14",
        "전공자/복수전공자": "N",
        "전공자정원포함여부": "N",
        "신청과목수": "6",
        "졸업신청": "N",
        "초수강여부": "Y",
        "총이수학점/졸업이수학점": "0.4285",
        "직전학기이수학점/학기당수강학점": "1.0000",
        "학년": "2",
        "수강여부": "X",
        "비고": ""
      },
      {
        "순위": "107",
        "마일리지": "14",
        "전공자/복수전공자": "N",
        "전공자정원포함여부": "N",
        "신청과목수": "6",
        "졸업신청": "N",
        "초수강여부": "Y",
        "총이수학점/졸업이수학점": "0.2222",
        "직전학기이수학점/학기당수강학점": "0.7631",
        "학년": "2",
        "수강여부": "X",
        "비고": ""
      },
      {
        "순위": "108",
        "마일리지": "13",
        "전공자/복수전공자": "N",
        "전공자정원포함여부": "N",
        "신청과목수": "6",
        "졸업신청": "Y",
        "초수강여부": "Y",
        "총이수학점/졸업이수학점": "0.9365",
        "직전학기이수학점/학기당수강학점": "0.6666",
        "학년": "4",
        "수강여부": "O",
        "비고": ""
      },
      {
        "순위": "109",
        "마일리지": "13",
        "전공자/복수전공자": "N",
        "전공자정원포함여부": "N",
        "신청과목수": "6",
        "졸업신청": "N",
        "초수강여부": "Y",
        "총이수학점/졸업이수학점": "0.7000",
        "직전학기이수학점/학기당수강학점": "1.0000",
        "학년": "3",
        "수강여부": "X",
        "비고": ""
      },
      {
        "순위": "110",
        "마일리지": "13",
        "전공자/복수전공자": "N",
        "전공자정원포함여부": "N",
        "신청과목수": "6",
        "졸업신청": "N",
        "초수강여부": "Y",
        "총이수학점/졸업이수학점": "0.6464",
        "직전학기이수학점/학기당수강학점": "0.7894",
        "학년": "4",
        "수강여부": "O",
        "비고": ""
      },
      {
        "순위": "111",
        "마일리지": "13",
        "전공자/복수전공자": "N",
        "전공자정원포함여부": "N",
        "신청과목수": "6",
        "졸업신청": "N",
        "초수강여부": "Y",
        "총이수학점/졸업이수학점": "0.5250",
        "직전학기이수학점/학기당수강학점": "0.8157",
        "학년": "3",
        "수강여부": "X",
        "비고": ""
      },
      {
        "순위": "112",
        "마일리지": "13",
        "전공자/복수전공자": "N",
        "전공자정원포함여부": "N",
        "신청과목수": "6",
        "졸업신청": "N",
        "초수강여부": "Y",
        "총이수학점/졸업이수학점": "0.4563",
        "직전학기이수학점/학기당수강학점": "1.0000",
        "학년": "2",
        "수강여부": "X",
        "비고": ""
      },
      {
        "순위": "113",
        "마일리지": "12",
        "전공자/복수전공자": "N",
        "전공자정원포함여부": "N",
        "신청과목수": "6",
        "졸업신청": "N",
        "초수강여부": "Y",
        "총이수학점/졸업이수학점": "0.7000",
        "직전학기이수학점/학기당수강학점": "0.9473",
        "학년": "3",
        "수강여부": "X",
        "비고": ""
      },
      {
        "순위": "114",
        "마일리지": "12",
        "전공자/복수전공자": "N",
        "전공자정원포함여부": "N",
        "신청과목수": "6",
        "졸업신청": "N",
        "초수강여부": "Y",
        "총이수학점/졸업이수학점": "0.6984",
        "직전학기이수학점/학기당수강학점": "1.0000",
        "학년": "3",
        "수강여부": "X",
        "비고": ""
      },
      {
        "순위": "115",
        "마일리지": "12",
        "전공자/복수전공자": "N",
        "전공자정원포함여부": "N",
        "신청과목수": "6",
        "졸업신청": "N",
        "초수강여부": "Y",
        "총이수학점/졸업이수학점": "0.5079",
        "직전학기이수학점/학기당수강학점": "0.9166",
        "학년": "2",
        "수강여부": "X",
        "비고": ""
      },
      {
        "순위": "116",
        "마일리지": "12",
        "전공자/복수전공자": "N",
        "전공자정원포함여부": "N",
        "신청과목수": "5",
        "졸업신청": "N",
        "초수강여부": "Y",
        "총이수학점/졸업이수학점": "0.3253",
        "직전학기이수학점/학기당수강학점": "1.0000",
        "학년": "2",
        "수강여부": "X",
        "비고": ""
      },
      {
        "순위": "117",
        "마일리지": "11",
        "전공자/복수전공자": "N",
        "전공자정원포함여부": "N",
        "신청과목수": "6",
        "졸업신청": "Y",
        "초수강여부": "Y",
        "총이수학점/졸업이수학점": "0.9071",
        "직전학기이수학점/학기당수강학점": "0.9473",
        "학년": "4",
        "수강여부": "O",
        "비고": ""
      },
      {
        "순위": "118",
        "마일리지": "11",
        "전공자/복수전공자": "N",
        "전공자정원포함여부": "N",
        "신청과목수": "6",
        "졸업신청": "Y",
        "초수강여부": "Y",
        "총이수학점/졸업이수학점": "0.8968",
        "직전학기이수학점/학기당수강학점": "1.0000",
        "학년": "4",
        "수강여부": "O",
        "비고": ""
      },
      {
        "순위": "119",
        "마일리지": "11",
        "전공자/복수전공자": "N",
        "전공자정원포함여부": "N",
        "신청과목수": "6",
        "졸업신청": "N",
        "초수강여부": "Y",
        "총이수학점/졸업이수학점": "0.8571",
        "직전학기이수학점/학기당수강학점": "1.0000",
        "학년": "4",
        "수강여부": "O",
        "비고": ""
      },
      {
        "순위": "120",
        "마일리지": "11",
        "전공자/복수전공자": "N",
        "전공자정원포함여부": "N",
        "신청과목수": "6",
        "졸업신청": "N",
        "초수강여부": "Y",
        "총이수학점/졸업이수학점": "0.7642",
        "직전학기이수학점/학기당수강학점": "1.0000",
        "학년": "3",
        "수강여부": "X",
        "비고": ""
      },
      {
        "순위": "121",
        "마일리지": "11",
        "전공자/복수전공자": "N",
        "전공자정원포함여부": "N",
        "신청과목수": "6",
        "졸업신청": "N",
        "초수강여부": "Y",
        "총이수학점/졸업이수학점": "0.7460",
        "직전학기이수학점/학기당수강학점": "1.0000",
        "학년": "3",
        "수강여부": "X",
        "비고": ""
      },
      {
        "순위": "122",
        "마일리지": "11",
        "전공자/복수전공자": "N",
        "전공자정원포함여부": "N",
        "신청과목수": "6",
        "졸업신청": "N",
        "초수강여부": "Y",
        "총이수학점/졸업이수학점": "0.4785",
        "직전학기이수학점/학기당수강학점": "0.7894",
        "학년": "3",
        "수강여부": "X",
        "비고": ""
      },
      {
        "순위": "123",
        "마일리지": "11",
        "전공자/복수전공자": "N",
        "전공자정원포함여부": "N",
        "신청과목수": "6",
        "졸업신청": "N",
        "초수강여부": "Y",
        "총이수학점/졸업이수학점": "0.4037",
        "직전학기이수학점/학기당수강학점": "0.9736",
        "학년": "2",
        "수강여부": "X",
        "비고": ""
      },
      {
        "순위": "124",
        "마일리지": "11",
        "전공자/복수전공자": "N",
        "전공자정원포함여부": "N",
        "신청과목수": "5",
        "졸업신청": "N",
        "초수강여부": "Y",
        "총이수학점/졸업이수학점": "0.9333",
        "직전학기이수학점/학기당수강학점": "1.0000",
        "학년": "4",
        "수강여부": "O",
        "비고": ""
      },
      {
        "순위": "125",
        "마일리지": "10",
        "전공자/복수전공자": "N",
        "전공자정원포함여부": "N",
        "신청과목수": "6",
        "졸업신청": "Y",
        "초수강여부": "Y",
        "총이수학점/졸업이수학점": "0.8642",
        "직전학기이수학점/학기당수강학점": "0.9736",
        "학년": "4",
        "수강여부": "O",
        "비고": ""
      },
      {
        "순위": "126",
        "마일리지": "10",
        "전공자/복수전공자": "N",
        "전공자정원포함여부": "N",
        "신청과목수": "6",
        "졸업신청": "N",
        "초수강여부": "Y",
        "총이수학점/졸업이수학점": "0.9126",
        "직전학기이수학점/학기당수강학점": "1.0000",
        "학년": "4",
        "수강여부": "O",
        "비고": ""
      },
      {
        "순위": "127",
        "마일리지": "10",
        "전공자/복수전공자": "N",
        "전공자정원포함여부": "N",
        "신청과목수": "6",
        "졸업신청": "N",
        "초수강여부": "Y",
        "총이수학점/졸업이수학점": "0.7714",
        "직전학기이수학점/학기당수강학점": "0.7894",
        "학년": "4",
        "수강여부": "X",
        "비고": ""
      },
      {
        "순위": "128",
        "마일리지": "10",
        "전공자/복수전공자": "N",
        "전공자정원포함여부": "N",
        "신청과목수": "6",
        "졸업신청": "N",
        "초수강여부": "Y",
        "총이수학점/졸업이수학점": "0.7349",
        "직전학기이수학점/학기당수강학점": "0.9473",
        "학년": "4",
        "수강여부": "X",
        "비고": ""
      },
      {
        "순위": "129",
        "마일리지": "10",
        "전공자/복수전공자": "N",
        "전공자정원포함여부": "N",
        "신청과목수": "6",
        "졸업신청": "N",
        "초수강여부": "Y",
        "총이수학점/졸업이수학점": "0.5555",
        "직전학기이수학점/학기당수강학점": "1.0000",
        "학년": "3",
        "수강여부": "X",
        "비고": ""
      },
      {
        "순위": "130",
        "마일리지": "10",
        "전공자/복수전공자": "N",
        "전공자정원포함여부": "N",
        "신청과목수": "6",
        "졸업신청": "N",
        "초수강여부": "Y",
        "총이수학점/졸업이수학점": "0.4246",
        "직전학기이수학점/학기당수강학점": "0.8611",
        "학년": "2",
        "수강여부": "X",
        "비고": ""
      },
      {
        "순위": "131",
        "마일리지": "10",
        "전공자/복수전공자": "N",
        "전공자정원포함여부": "N",
        "신청과목수": "6",
        "졸업신청": "N",
        "초수강여부": "Y",
        "총이수학점/졸업이수학점": "0.3607",
        "직전학기이수학점/학기당수강학점": "1.0000",
        "학년": "2",
        "수강여부": "X",
        "비고": ""
      },
      {
        "순위": "132",
        "마일리지": "10",
        "전공자/복수전공자": "N",
        "전공자정원포함여부": "N",
        "신청과목수": "5",
        "졸업신청": "N",
        "초수강여부": "Y",
        "총이수학점/졸업이수학점": "0.4087",
        "직전학기이수학점/학기당수강학점": "0.7500",
        "학년": "2",
        "수강여부": "X",
        "비고": ""
      },
      {
        "순위": "133",
        "마일리지": "9",
        "전공자/복수전공자": "N",
        "전공자정원포함여부": "N",
        "신청과목수": "6",
        "졸업신청": "N",
        "초수강여부": "Y",
        "총이수학점/졸업이수학점": "0.8650",
        "직전학기이수학점/학기당수강학점": "1.0000",
        "학년": "4",
        "수강여부": "X",
        "비고": ""
      },
      {
        "순위": "134",
        "마일리지": "9",
        "전공자/복수전공자": "N",
        "전공자정원포함여부": "N",
        "신청과목수": "6",
        "졸업신청": "N",
        "초수강여부": "Y",
        "총이수학점/졸업이수학점": "0.7936",
        "직전학기이수학점/학기당수강학점": "1.0000",
        "학년": "4",
        "수강여부": "X",
        "비고": ""
      },
      {
        "순위": "135",
        "마일리지": "9",
        "전공자/복수전공자": "N",
        "전공자정원포함여부": "N",
        "신청과목수": "6",
        "졸업신청": "N",
        "초수강여부": "Y",
        "총이수학점/졸업이수학점": "0.2962",
        "직전학기이수학점/학기당수강학점": "0.8947",
        "학년": "2",
        "수강여부": "X",
        "비고": ""
      },
      {
        "순위": "136",
        "마일리지": "9",
        "전공자/복수전공자": "N",
        "전공자정원포함여부": "N",
        "신청과목수": "6",
        "졸업신청": "N",
        "초수강여부": "Y",
        "총이수학점/졸업이수학점": "0.2817",
        "직전학기이수학점/학기당수강학점": "0.6944",
        "학년": "2",
        "수강여부": "X",
        "비고": ""
      },
      {
        "순위": "137",
        "마일리지": "8",
        "전공자/복수전공자": "N",
        "전공자정원포함여부": "N",
        "신청과목수": "6",
        "졸업신청": "N",
        "초수강여부": "Y",
        "총이수학점/졸업이수학점": "0.8253",
        "직전학기이수학점/학기당수강학점": "1.0000",
        "학년": "4",
        "수강여부": "X",
        "비고": ""
      },
      {
        "순위": "138",
        "마일리지": "8",
        "전공자/복수전공자": "N",
        "전공자정원포함여부": "N",
        "신청과목수": "6",
        "졸업신청": "N",
        "초수강여부": "Y",
        "총이수학점/졸업이수학점": "0.8015",
        "직전학기이수학점/학기당수강학점": "0.8888",
        "학년": "3",
        "수강여부": "X",
        "비고": ""
      },
      {
        "순위": "139",
        "마일리지": "8",
        "전공자/복수전공자": "N",
        "전공자정원포함여부": "N",
        "신청과목수": "6",
        "졸업신청": "N",
        "초수강여부": "Y",
        "총이수학점/졸업이수학점": "0.7571",
        "직전학기이수학점/학기당수강학점": "0.9473",
        "학년": "4",
        "수강여부": "X",
        "비고": ""
      },
      {
        "순위": "140",
        "마일리지": "8",
        "전공자/복수전공자": "N",
        "전공자정원포함여부": "N",
        "신청과목수": "6",
        "졸업신청": "N",
        "초수강여부": "Y",
        "총이수학점/졸업이수학점": "0.6984",
        "직전학기이수학점/학기당수강학점": "0.6666",
        "학년": "4",
        "수강여부": "X",
        "비고": ""
      },
      {
        "순위": "141",
        "마일리지": "8",
        "전공자/복수전공자": "N",
        "전공자정원포함여부": "N",
        "신청과목수": "6",
        "졸업신청": "N",
        "초수강여부": "Y",
        "총이수학점/졸업이수학점": "0.6740",
        "직전학기이수학점/학기당수강학점": "0.9473",
        "학년": "4",
        "수강여부": "X",
        "비고": ""
      },
      {
        "순위": "142",
        "마일리지": "8",
        "전공자/복수전공자": "N",
        "전공자정원포함여부": "N",
        "신청과목수": "6",
        "졸업신청": "N",
        "초수강여부": "Y",
        "총이수학점/졸업이수학점": "0.6714",
        "직전학기이수학점/학기당수강학점": "0.9473",
        "학년": "3",
        "수강여부": "X",
        "비고": ""
      },
      {
        "순위": "143",
        "마일리지": "8",
        "전공자/복수전공자": "N",
        "전공자정원포함여부": "N",
        "신청과목수": "6",
        "졸업신청": "N",
        "초수강여부": "Y",
        "총이수학점/졸업이수학점": "0.3678",
        "직전학기이수학점/학기당수강학점": "0.9736",
        "학년": "2",
        "수강여부": "X",
        "비고": ""
      },
      {
        "순위": "144",
        "마일리지": "8",
        "전공자/복수전공자": "N",
        "전공자정원포함여부": "N",
        "신청과목수": "6",
        "졸업신청": "N",
        "초수강여부": "Y",
        "총이수학점/졸업이수학점": "0.3373",
        "직전학기이수학점/학기당수강학점": "0.9473",
        "학년": "2",
        "수강여부": "X",
        "비고": ""
      },
      {
        "순위": "145",
        "마일리지": "8",
        "전공자/복수전공자": "N",
        "전공자정원포함여부": "N",
        "신청과목수": "6",
        "졸업신청": "N",
        "초수강여부": "Y",
        "총이수학점/졸업이수학점": "0.1962",
        "직전학기이수학점/학기당수강학점": "0.8157",
        "학년": "2",
        "수강여부": "X",
        "비고": ""
      },
      {
        "순위": "146",
        "마일리지": "7",
        "전공자/복수전공자": "N",
        "전공자정원포함여부": "N",
        "신청과목수": "6",
        "졸업신청": "Y",
        "초수강여부": "Y",
        "총이수학점/졸업이수학점": "1.0000",
        "직전학기이수학점/학기당수강학점": "0.7894",
        "학년": "4",
        "수강여부": "X",
        "비고": ""
      },
      {
        "순위": "147",
        "마일리지": "7",
        "전공자/복수전공자": "N",
        "전공자정원포함여부": "N",
        "신청과목수": "6",
        "졸업신청": "N",
        "초수강여부": "Y",
        "총이수학점/졸업이수학점": "0.8174",
        "직전학기이수학점/학기당수강학점": "0.6666",
        "학년": "4",
        "수강여부": "X",
        "비고": ""
      },
      {
        "순위": "148",
        "마일리지": "7",
        "전공자/복수전공자": "N",
        "전공자정원포함여부": "N",
        "신청과목수": "6",
        "졸업신청": "N",
        "초수강여부": "Y",
        "총이수학점/졸업이수학점": "0.6285",
        "직전학기이수학점/학기당수강학점": "0.7894",
        "학년": "3",
        "수강여부": "X",
        "비고": ""
      },
      {
        "순위": "149",
        "마일리지": "7",
        "전공자/복수전공자": "N",
        "전공자정원포함여부": "N",
        "신청과목수": "6",
        "졸업신청": "N",
        "초수강여부": "Y",
        "총이수학점/졸업이수학점": "0.6035",
        "직전학기이수학점/학기당수강학점": "0.9736",
        "학년": "3",
        "수강여부": "X",
        "비고": ""
      },
      {
        "순위": "150",
        "마일리지": "7",
        "전공자/복수전공자": "N",
        "전공자정원포함여부": "N",
        "신청과목수": "6",
        "졸업신청": "N",
        "초수강여부": "Y",
        "총이수학점/졸업이수학점": "0.4888",
        "직전학기이수학점/학기당수강학점": "0.8157",
        "학년": "3",
        "수강여부": "X",
        "비고": ""
      },
      {
        "순위": "151",
        "마일리지": "6",
        "전공자/복수전공자": "N",
        "전공자정원포함여부": "N",
        "신청과목수": "6",
        "졸업신청": "N",
        "초수강여부": "Y",
        "총이수학점/졸업이수학점": "0.7698",
        "직전학기이수학점/학기당수강학점": "1.0000",
        "학년": "4",
        "수강여부": "X",
        "비고": ""
      },
      {
        "순위": "152",
        "마일리지": "6",
        "전공자/복수전공자": "N",
        "전공자정원포함여부": "N",
        "신청과목수": "6",
        "졸업신청": "N",
        "초수강여부": "Y",
        "총이수학점/졸업이수학점": "0.6825",
        "직전학기이수학점/학기당수강학점": "0.8333",
        "학년": "3",
        "수강여부": "X",
        "비고": ""
      },
      {
        "순위": "153",
        "마일리지": "5",
        "전공자/복수전공자": "N",
        "전공자정원포함여부": "N",
        "신청과목수": "6",
        "졸업신청": "N",
        "초수강여부": "Y",
        "총이수학점/졸업이수학점": "0.5952",
        "직전학기이수학점/학기당수강학점": "1.0000",
        "학년": "3",
        "수강여부": "X",
        "비고": ""
      },
      {
        "순위": "154",
        "마일리지": "5",
        "전공자/복수전공자": "N",
        "전공자정원포함여부": "N",
        "신청과목수": "6",
        "졸업신청": "N",
        "초수강여부": "Y",
        "총이수학점/졸업이수학점": "0.5285",
        "직전학기이수학점/학기당수강학점": "0.9736",
        "학년": "3",
        "수강여부": "X",
        "비고": ""
      },
      {
        "순위": "155",
        "마일리지": "5",
        "전공자/복수전공자": "N",
        "전공자정원포함여부": "N",
        "신청과목수": "6",
        "졸업신청": "N",
        "초수강여부": "Y",
        "총이수학점/졸업이수학점": "0.4629",
        "직전학기이수학점/학기당수강학점": "0.9736",
        "학년": "2",
        "수강여부": "X",
        "비고": ""
      },
      {
        "순위": "156",
        "마일리지": "5",
        "전공자/복수전공자": "N",
        "전공자정원포함여부": "N",
        "신청과목수": "6",
        "졸업신청": "N",
        "초수강여부": "Y",
        "총이수학점/졸업이수학점": "0.4563",
        "직전학기이수학점/학기당수강학점": "1.0000",
        "학년": "2",
        "수강여부": "X",
        "비고": ""
      },
      {
        "순위": "157",
        "마일리지": "5",
        "전공자/복수전공자": "N",
        "전공자정원포함여부": "N",
        "신청과목수": "6",
        "졸업신청": "N",
        "초수강여부": "Y",
        "총이수학점/졸업이수학점": "0.4523",
        "직전학기이수학점/학기당수강학점": "1.0000",
        "학년": "2",
        "수강여부": "X",
        "비고": ""
      },
      {
        "순위": "158",
        "마일리지": "5",
        "전공자/복수전공자": "N",
        "전공자정원포함여부": "N",
        "신청과목수": "6",
        "졸업신청": "N",
        "초수강여부": "Y",
        "총이수학점/졸업이수학점": "0.4250",
        "직전학기이수학점/학기당수강학점": "0.9736",
        "학년": "2",
        "수강여부": "X",
        "비고": ""
      },
      {
        "순위": "159",
        "마일리지": "5",
        "전공자/복수전공자": "N",
        "전공자정원포함여부": "N",
        "신청과목수": "6",
        "졸업신청": "N",
        "초수강여부": "Y",
        "총이수학점/졸업이수학점": "0.4087",
        "직전학기이수학점/학기당수강학점": "0.8611",
        "학년": "2",
        "수강여부": "X",
        "비고": ""
      },
      {
        "순위": "160",
        "마일리지": "5",
        "전공자/복수전공자": "N",
        "전공자정원포함여부": "N",
        "신청과목수": "6",
        "졸업신청": "N",
        "초수강여부": "Y",
        "총이수학점/졸업이수학점": "0.4071",
        "직전학기이수학점/학기당수강학점": "0.8684",
        "학년": "2",
        "수강여부": "X",
        "비고": ""
      },
      {
        "순위": "161",
        "마일리지": "5",
        "전공자/복수전공자": "N",
        "전공자정원포함여부": "N",
        "신청과목수": "6",
        "졸업신청": "N",
        "초수강여부": "Y",
        "총이수학점/졸업이수학점": "0.3892",
        "직전학기이수학점/학기당수강학점": "0.6578",
        "학년": "2",
        "수강여부": "X",
        "비고": ""
      },
      {
        "순위": "162",
        "마일리지": "5",
        "전공자/복수전공자": "N",
        "전공자정원포함여부": "N",
        "신청과목수": "6",
        "졸업신청": "N",
        "초수강여부": "Y",
        "총이수학점/졸업이수학점": "0.3535",
        "직전학기이수학점/학기당수강학점": "0.8684",
        "학년": "2",
        "수강여부": "X",
        "비고": ""
      },
      {
        "순위": "163",
        "마일리지": "5",
        "전공자/복수전공자": "N",
        "전공자정원포함여부": "N",
        "신청과목수": "6",
        "졸업신청": "N",
        "초수강여부": "Y",
        "총이수학점/졸업이수학점": "0.3407",
        "직전학기이수학점/학기당수강학점": "0.8684",
        "학년": "2",
        "수강여부": "X",
        "비고": ""
      },
      {
        "순위": "164",
        "마일리지": "4",
        "전공자/복수전공자": "N",
        "전공자정원포함여부": "N",
        "신청과목수": "6",
        "졸업신청": "N",
        "초수강여부": "Y",
        "총이수학점/졸업이수학점": "0.4166",
        "직전학기이수학점/학기당수강학점": "1.0000",
        "학년": "2",
        "수강여부": "X",
        "비고": ""
      },
      {
        "순위": "165",
        "마일리지": "3",
        "전공자/복수전공자": "N",
        "전공자정원포함여부": "N",
        "신청과목수": "6",
        "졸업신청": "N",
        "초수강여부": "Y",
        "총이수학점/졸업이수학점": "0.8253",
        "직전학기이수학점/학기당수강학점": "1.0000",
        "학년": "4",
        "수강여부": "X",
        "비고": ""
      },
      {
        "순위": "166",
        "마일리지": "3",
        "전공자/복수전공자": "N",
        "전공자정원포함여부": "N",
        "신청과목수": "6",
        "졸업신청": "N",
        "초수강여부": "Y",
        "총이수학점/졸업이수학점": "0.6666",
        "직전학기이수학점/학기당수강학점": "0.9473",
        "학년": "4",
        "수강여부": "X",
        "비고": ""
      },
      {
        "순위": "167",
        "마일리지": "3",
        "전공자/복수전공자": "N",
        "전공자정원포함여부": "N",
        "신청과목수": "6",
        "졸업신청": "N",
        "초수강여부": "Y",
        "총이수학점/졸업이수학점": "0.4285",
        "직전학기이수학점/학기당수강학점": "1.0000",
        "학년": "2",
        "수강여부": "X",
        "비고": ""
      },
      {
        "순위": "168",
        "마일리지": "2",
        "전공자/복수전공자": "N",
        "전공자정원포함여부": "N",
        "신청과목수": "6",
        "졸업신청": "Y",
        "초수강여부": "Y",
        "총이수학점/졸업이수학점": "1.0000",
        "직전학기이수학점/학기당수강학점": "0.1666",
        "학년": "4",
        "수강여부": "X",
        "비고": ""
      },
      {
        "순위": "169",
        "마일리지": "2",
        "전공자/복수전공자": "N",
        "전공자정원포함여부": "N",
        "신청과목수": "6",
        "졸업신청": "N",
        "초수강여부": "Y",
        "총이수학점/졸업이수학점": "0.7000",
        "직전학기이수학점/학기당수강학점": "0.9473",
        "학년": "3",
        "수강여부": "X",
        "비고": ""
      },
      {
        "순위": "170",
        "마일리지": "2",
        "전공자/복수전공자": "N",
        "전공자정원포함여부": "N",
        "신청과목수": "6",
        "졸업신청": "N",
        "초수강여부": "Y",
        "총이수학점/졸업이수학점": "0.6928",
        "직전학기이수학점/학기당수강학점": "1.0000",
        "학년": "3",
        "수강여부": "X",
        "비고": ""
      },
      {
        "순위": "171",
        "마일리지": "2",
        "전공자/복수전공자": "N",
        "전공자정원포함여부": "N",
        "신청과목수": "6",
        "졸업신청": "N",
        "초수강여부": "Y",
        "총이수학점/졸업이수학점": "0.3888",
        "직전학기이수학점/학기당수강학점": "0.8611",
        "학년": "2",
        "수강여부": "X",
        "비고": ""
      },
      {
        "순위": "172",
        "마일리지": "1",
        "전공자/복수전공자": "N",
        "전공자정원포함여부": "N",
        "신청과목수": "6",
        "졸업신청": "Y",
        "초수강여부": "Y",
        "총이수학점/졸업이수학점": "1.0000",
        "직전학기이수학점/학기당수강학점": "0.9473",
        "학년": "4",
        "수강여부": "X",
        "비고": ""
      },
      {
        "순위": "173",
        "마일리지": "1",
        "전공자/복수전공자": "N",
        "전공자정원포함여부": "N",
        "신청과목수": "6",
        "졸업신청": "Y",
        "초수강여부": "Y",
        "총이수학점/졸업이수학점": "0.9285",
        "직전학기이수학점/학기당수강학점": "0.9473",
        "학년": "4",
        "수강여부": "X",
        "비고": ""
      },
      {
        "순위": "174",
        "마일리지": "1",
        "전공자/복수전공자": "N",
        "전공자정원포함여부": "N",
        "신청과목수": "6",
        "졸업신청": "Y",
        "초수강여부": "Y",
        "총이수학점/졸업이수학점": "0.9285",
        "직전학기이수학점/학기당수강학점": "0.8333",
        "학년": "4",
        "수강여부": "X",
        "비고": ""
      },
      {
        "순위": "175",
        "마일리지": "1",
        "전공자/복수전공자": "N",
        "전공자정원포함여부": "N",
        "신청과목수": "6",
        "졸업신청": "N",
        "초수강여부": "Y",
        "총이수학점/졸업이수학점": "0.7777",
        "직전학기이수학점/학기당수강학점": "1.0000",
        "학년": "4",
        "수강여부": "X",
        "비고": ""
      },
      {
        "순위": "176",
        "마일리지": "1",
        "전공자/복수전공자": "N",
        "전공자정원포함여부": "N",
        "신청과목수": "6",
        "졸업신청": "N",
        "초수강여부": "Y",
        "총이수학점/졸업이수학점": "0.6814",
        "직전학기이수학점/학기당수강학점": "0.9473",
        "학년": "4",
        "수강여부": "X",
        "비고": ""
      },
      {
        "순위": "177",
        "마일리지": "1",
        "전공자/복수전공자": "N",
        "전공자정원포함여부": "N",
        "신청과목수": "6",
        "졸업신청": "N",
        "초수강여부": "Y",
        "총이수학점/졸업이수학점": "0.6626",
        "직전학기이수학점/학기당수강학점": "0.8611",
        "학년": "3",
        "수강여부": "X",
        "비고": ""
      },
      {
        "순위": "178",
        "마일리지": "1",
        "전공자/복수전공자": "N",
        "전공자정원포함여부": "N",
        "신청과목수": "6",
        "졸업신청": "N",
        "초수강여부": "Y",
        "총이수학점/졸업이수학점": "0.6222",
        "직전학기이수학점/학기당수강학점": "0.7894",
        "학년": "3",
        "수강여부": "X",
        "비고": ""
      },
      {
        "순위": "179",
        "마일리지": "1",
        "전공자/복수전공자": "N",
        "전공자정원포함여부": "N",
        "신청과목수": "6",
        "졸업신청": "N",
        "초수강여부": "Y",
        "총이수학점/졸업이수학점": "0.5240",
        "직전학기이수학점/학기당수강학점": "0.9473",
        "학년": "3",
        "수강여부": "X",
        "비고": ""
      },
      {
        "순위": "180",
        "마일리지": "1",
        "전공자/복수전공자": "N",
        "전공자정원포함여부": "N",
        "신청과목수": "6",
        "졸업신청": "N",
        "초수강여부": "Y",
        "총이수학점/졸업이수학점": "0.5000",
        "직전학기이수학점/학기당수강학점": "0.8157",
        "학년": "3",
        "수강여부": "X",
        "비고": ""
      },
      {
        "순위": "181",
        "마일리지": "1",
        "전공자/복수전공자": "N",
        "전공자정원포함여부": "N",
        "신청과목수": "6",
        "졸업신청": "N",
        "초수강여부": "Y",
        "총이수학점/졸업이수학점": "0.4801",
        "직전학기이수학점/학기당수강학점": "1.0000",
        "학년": "2",
        "수강여부": "X",
        "비고": ""
      },
      {
        "순위": "182",
        "마일리지": "1",
        "전공자/복수전공자": "N",
        "전공자정원포함여부": "N",
        "신청과목수": "6",
        "졸업신청": "N",
        "초수강여부": "Y",
        "총이수학점/졸업이수학점": "0.4535",
        "직전학기이수학점/학기당수강학점": "0.9736",
        "학년": "2",
        "수강여부": "X",
        "비고": ""
      },
      {
        "순위": "183",
        "마일리지": "1",
        "전공자/복수전공자": "N",
        "전공자정원포함여부": "N",
        "신청과목수": "6",
        "졸업신청": "N",
        "초수강여부": "Y",
        "총이수학점/졸업이수학점": "0.3357",
        "직전학기이수학점/학기당수강학점": "0.6315",
        "학년": "2",
        "수강여부": "X",
        "비고": ""
      },
      {
        "순위": "184",
        "마일리지": "1",
        "전공자/복수전공자": "N",
        "전공자정원포함여부": "N",
        "신청과목수": "6",
        "졸업신청": "N",
        "초수강여부": "Y",
        "총이수학점/졸업이수학점": "0.3222",
        "직전학기이수학점/학기당수강학점": "0.9736",
        "학년": "2",
        "수강여부": "X",
        "비고": ""
      }
    ]
  }
}