{
  "20202": {
    "CAUTION": {
      "교육과학대학": {
        "체육교육학전공": [
          "대면강의",
          "P/NP평가 과목"
        ]
      }
    },
    "LECT_DATA": {
      "학정번호-분반-실습": "PED2002-09-00",
      "과목명": "UT세미나(운동생리학과다이어트)",
      "학점": "1",
      "담당교수": "박병준",
      "강의시간": "화5",
      "강의실": "스포츠109",
      "정원": "10",
      "참여인원": "2",
      "전공자정원": "0",
      "2전공포함": "N",
      "1학년정원": "0",
      "2학년정원": "0",
      "3학년정원": "0",
      "4학년정원": "0",
      "교환학생 가능여부": "O",
      "Max Mileage(limit)": "36",
      "Mileage_minimum": "1",
      "Mileage_maximum": "2",
      "Mileage_average": "1.5"
    },
    "RESULT_DATA": [
      {
        "순위": "1",
        "마일리지": "2",
        "전공자/복수전공자": "Y",
        "전공자정원포함여부": "Y",
        "신청과목수": "6",
        "졸업신청": "Y",
        "초수강여부": "Y",
        "총이수학점/졸업이수학점": "0.9246",
        "직전학기이수학점/학기당수강학점": "0.9166",
        "학년": "4",
        "수강여부": "O",
        "비고": ""
      },
      {
        "순위": "2",
        "마일리지": "1",
        "전공자/복수전공자": "N",
        "전공자정원포함여부": "N",
        "신청과목수": "6",
        "졸업신청": "N",
        "초수강여부": "Y",
        "총이수학점/졸업이수학점": "0.6428",
        "직전학기이수학점/학기당수강학점": "0.8611",
        "학년": "3",
        "수강여부": "O",
        "비고": ""
      }
    ],
    "SYLLABUS_DATA": {
      "교재 및 참고문헌": [
        "○ 운동과 에너지 대사, 백일영(2009)",
        "",
        "○ 운동생리학과 운동처방 <이론과 실험>, 백일영(2012)",
        "",
        "○ 2015 한국인 영양소 섭취기준, 보건복지부(2015)"
      ]
    }
  },
  "20201": {
    "LECT_DATA": {
      "학정번호": "PED2002-09-00",
      "과목명": "UT세미나(질환별운동처방및검사의기초)"
    },
    "SYLLABUS_DATA": {
      "교재 및 참고문헌": [
        "○ Acsm's Guidelines for Exercise Testing and Prescription, LippincottWilliams & Wilkins(2017)",
        "\r○ Acsm's Exercise Management for Persons With Chronic Diseases and Disabilities, American College of Sports Medicine, Human Kinetics(2016)"
      ]
    }
  }
}