{
  "20171": {
    "CAUTION": {
      "언더우드국제대학": {
        "융합사회과학부-사회정의리더십": [
          "영어강의",
          "UIC students only"
        ]
      }
    },
    "LECT_DATA": {
      "학정번호-분반-실습": "JCL4002-01-00",
      "과목명": "THE RULE OF LAW IN THEORY AND PRACTICE",
      "학점": "3",
      "담당교수": "콜만프란시스카",
      "강의시간": "월5,수5,6",
      "강의실": "새천206",
      "정원": "18",
      "참여인원": "17",
      "전공자정원": "18",
      "2전공포함": "Y",
      "1학년정원": "0",
      "2학년정원": "0",
      "3학년정원": "0",
      "4학년정원": "0",
      "교환학생 가능여부": "X",
      "Max Mileage(limit)": "36",
      "Mileage_minimum": "1",
      "Mileage_maximum": "36",
      "Mileage_average": "10.35"
    },
    "RESULT_DATA": [
      {
        "순위": "1",
        "마일리지": "36",
        "전공자/복수전공자": "Y",
        "전공자정원포함여부": "Y",
        "신청과목수": "5",
        "졸업신청": "N",
        "초수강여부": "Y",
        "총이수학점/졸업이수학점": "0.5952",
        "직전학기이수학점/학기당수강학점": "1.0000",
        "학년": "3",
        "수강여부": "O",
        "비고": ""
      },
      {
        "순위": "2",
        "마일리지": "36",
        "전공자/복수전공자": "Y",
        "전공자정원포함여부": "Y",
        "신청과목수": "4",
        "졸업신청": "N",
        "초수강여부": "Y",
        "총이수학점/졸업이수학점": "1.0000",
        "직전학기이수학점/학기당수강학점": "1.0000",
        "학년": "4",
        "수강여부": "O",
        "비고": ""
      },
      {
        "순위": "3",
        "마일리지": "20",
        "전공자/복수전공자": "Y",
        "전공자정원포함여부": "Y",
        "신청과목수": "5",
        "졸업신청": "N",
        "초수강여부": "Y",
        "총이수학점/졸업이수학점": "0.6884",
        "직전학기이수학점/학기당수강학점": "0.8888",
        "학년": "3",
        "수강여부": "O",
        "비고": ""
      },
      {
        "순위": "4",
        "마일리지": "15",
        "전공자/복수전공자": "Y",
        "전공자정원포함여부": "Y",
        "신청과목수": "4",
        "졸업신청": "N",
        "초수강여부": "Y",
        "총이수학점/졸업이수학점": "0.7936",
        "직전학기이수학점/학기당수강학점": "0.8333",
        "학년": "4",
        "수강여부": "O",
        "비고": ""
      },
      {
        "순위": "5",
        "마일리지": "12",
        "전공자/복수전공자": "Y",
        "전공자정원포함여부": "Y",
        "신청과목수": "6",
        "졸업신청": "N",
        "초수강여부": "Y",
        "총이수학점/졸업이수학점": "0.5952",
        "직전학기이수학점/학기당수강학점": "1.0000",
        "학년": "3",
        "수강여부": "O",
        "비고": ""
      },
      {
        "순위": "6",
        "마일리지": "12",
        "전공자/복수전공자": "Y",
        "전공자정원포함여부": "Y",
        "신청과목수": "6",
        "졸업신청": "N",
        "초수강여부": "Y",
        "총이수학점/졸업이수학점": "0.5238",
        "직전학기이수학점/학기당수강학점": "1.0000",
        "학년": "3",
        "수강여부": "O",
        "비고": ""
      },
      {
        "순위": "7",
        "마일리지": "12",
        "전공자/복수전공자": "Y",
        "전공자정원포함여부": "Y",
        "신청과목수": "4",
        "졸업신청": "N",
        "초수강여부": "Y",
        "총이수학점/졸업이수학점": "0.7857",
        "직전학기이수학점/학기당수강학점": "0.8333",
        "학년": "4",
        "수강여부": "O",
        "비고": ""
      },
      {
        "순위": "8",
        "마일리지": "8",
        "전공자/복수전공자": "Y",
        "전공자정원포함여부": "Y",
        "신청과목수": "5",
        "졸업신청": "N",
        "초수강여부": "Y",
        "총이수학점/졸업이수학점": "0.8809",
        "직전학기이수학점/학기당수강학점": "0.8333",
        "학년": "4",
        "수강여부": "O",
        "비고": ""
      },
      {
        "순위": "9",
        "마일리지": "6",
        "전공자/복수전공자": "Y",
        "전공자정원포함여부": "Y",
        "신청과목수": "6",
        "졸업신청": "N",
        "초수강여부": "Y",
        "총이수학점/졸업이수학점": "0.8253",
        "직전학기이수학점/학기당수강학점": "0.8333",
        "학년": "4",
        "수강여부": "O",
        "비고": ""
      },
      {
        "순위": "10",
        "마일리지": "5",
        "전공자/복수전공자": "Y",
        "전공자정원포함여부": "Y",
        "신청과목수": "6",
        "졸업신청": "N",
        "초수강여부": "Y",
        "총이수학점/졸업이수학점": "0.6388",
        "직전학기이수학점/학기당수강학점": "1.0000",
        "학년": "3",
        "수강여부": "O",
        "비고": ""
      },
      {
        "순위": "11",
        "마일리지": "3",
        "전공자/복수전공자": "Y",
        "전공자정원포함여부": "Y",
        "신청과목수": "6",
        "졸업신청": "N",
        "초수강여부": "Y",
        "총이수학점/졸업이수학점": "0.8888",
        "직전학기이수학점/학기당수강학점": "0.8333",
        "학년": "4",
        "수강여부": "O",
        "비고": ""
      },
      {
        "순위": "12",
        "마일리지": "3",
        "전공자/복수전공자": "Y",
        "전공자정원포함여부": "Y",
        "신청과목수": "6",
        "졸업신청": "N",
        "초수강여부": "Y",
        "총이수학점/졸업이수학점": "0.6746",
        "직전학기이수학점/학기당수강학점": "0.6666",
        "학년": "3",
        "수강여부": "O",
        "비고": ""
      },
      {
        "순위": "13",
        "마일리지": "3",
        "전공자/복수전공자": "Y",
        "전공자정원포함여부": "Y",
        "신청과목수": "6",
        "졸업신청": "N",
        "초수강여부": "Y",
        "총이수학점/졸업이수학점": "0.5476",
        "직전학기이수학점/학기당수강학점": "1.0000",
        "학년": "3",
        "수강여부": "O",
        "비고": ""
      },
      {
        "순위": "14",
        "마일리지": "2",
        "전공자/복수전공자": "Y",
        "전공자정원포함여부": "Y",
        "신청과목수": "6",
        "졸업신청": "N",
        "초수강여부": "Y",
        "총이수학점/졸업이수학점": "0.5674",
        "직전학기이수학점/학기당수강학점": "1.0000",
        "학년": "3",
        "수강여부": "O",
        "비고": ""
      },
      {
        "순위": "15",
        "마일리지": "1",
        "전공자/복수전공자": "Y",
        "전공자정원포함여부": "Y",
        "신청과목수": "6",
        "졸업신청": "Y",
        "초수강여부": "Y",
        "총이수학점/졸업이수학점": "0.8650",
        "직전학기이수학점/학기당수강학점": "0.6666",
        "학년": "4",
        "수강여부": "O",
        "비고": ""
      },
      {
        "순위": "16",
        "마일리지": "1",
        "전공자/복수전공자": "Y",
        "전공자정원포함여부": "Y",
        "신청과목수": "6",
        "졸업신청": "N",
        "초수강여부": "Y",
        "총이수학점/졸업이수학점": "0.5674",
        "직전학기이수학점/학기당수강학점": "1.0000",
        "학년": "3",
        "수강여부": "O",
        "비고": ""
      },
      {
        "순위": "17",
        "마일리지": "1",
        "전공자/복수전공자": "Y",
        "전공자정원포함여부": "Y",
        "신청과목수": "5",
        "졸업신청": "N",
        "초수강여부": "Y",
        "총이수학점/졸업이수학점": "0.5555",
        "직전학기이수학점/학기당수강학점": "0.8055",
        "학년": "3",
        "수강여부": "O",
        "비고": ""
      }
    ]
  }
}