{
  "20191": {
    "CAUTION": {
      "생명시스템대학": {
        "생명공학전공": [
          "절대평가"
        ]
      }
    },
    "LECT_DATA": {
      "학정번호-분반-실습": "BTE3104-01-00",
      "과목명": "의약생물소재화학",
      "학점": "3",
      "담당교수": "한균희",
      "강의시간": "월6,목6,7",
      "강의실": "공A579",
      "정원": "50",
      "참여인원": "30",
      "전공자정원": "0",
      "2전공포함": "N",
      "1학년정원": "0",
      "2학년정원": "0",
      "3학년정원": "0",
      "4학년정원": "0",
      "교환학생 가능여부": "O",
      "Max Mileage(limit)": "36",
      "Mileage_minimum": "1",
      "Mileage_maximum": "36",
      "Mileage_average": "4.9"
    },
    "RESULT_DATA": [
      {
        "순위": "1",
        "마일리지": "36",
        "전공자/복수전공자": "Y",
        "전공자정원포함여부": "Y",
        "신청과목수": "6",
        "졸업신청": "N",
        "초수강여부": "Y",
        "총이수학점/졸업이수학점": "0.8250",
        "직전학기이수학점/학기당수강학점": "0.9473",
        "학년": "4",
        "수강여부": "O",
        "비고": ""
      },
      {
        "순위": "2",
        "마일리지": "15",
        "전공자/복수전공자": "Y",
        "전공자정원포함여부": "Y",
        "신청과목수": "6",
        "졸업신청": "N",
        "초수강여부": "Y",
        "총이수학점/졸업이수학점": "0.6142",
        "직전학기이수학점/학기당수강학점": "0.9473",
        "학년": "4",
        "수강여부": "O",
        "비고": ""
      },
      {
        "순위": "3",
        "마일리지": "10",
        "전공자/복수전공자": "Y",
        "전공자정원포함여부": "Y",
        "신청과목수": "6",
        "졸업신청": "N",
        "초수강여부": "Y",
        "총이수학점/졸업이수학점": "0.5250",
        "직전학기이수학점/학기당수강학점": "1.0000",
        "학년": "3",
        "수강여부": "O",
        "비고": ""
      },
      {
        "순위": "4",
        "마일리지": "10",
        "전공자/복수전공자": "Y",
        "전공자정원포함여부": "Y",
        "신청과목수": "5",
        "졸업신청": "N",
        "초수강여부": "Y",
        "총이수학점/졸업이수학점": "0.8857",
        "직전학기이수학점/학기당수강학점": "1.0000",
        "학년": "4",
        "수강여부": "O",
        "비고": ""
      },
      {
        "순위": "5",
        "마일리지": "9",
        "전공자/복수전공자": "Y",
        "전공자정원포함여부": "Y",
        "신청과목수": "6",
        "졸업신청": "N",
        "초수강여부": "Y",
        "총이수학점/졸업이수학점": "0.7464",
        "직전학기이수학점/학기당수강학점": "0.7894",
        "학년": "4",
        "수강여부": "O",
        "비고": ""
      },
      {
        "순위": "6",
        "마일리지": "8",
        "전공자/복수전공자": "Y",
        "전공자정원포함여부": "Y",
        "신청과목수": "6",
        "졸업신청": "Y",
        "초수강여부": "Y",
        "총이수학점/졸업이수학점": "0.8785",
        "직전학기이수학점/학기당수강학점": "0.9473",
        "학년": "4",
        "수강여부": "O",
        "비고": ""
      },
      {
        "순위": "7",
        "마일리지": "8",
        "전공자/복수전공자": "Y",
        "전공자정원포함여부": "Y",
        "신청과목수": "6",
        "졸업신청": "N",
        "초수강여부": "Y",
        "총이수학점/졸업이수학점": "0.7071",
        "직전학기이수학점/학기당수강학점": "0.9736",
        "학년": "3",
        "수강여부": "O",
        "비고": ""
      },
      {
        "순위": "8",
        "마일리지": "6",
        "전공자/복수전공자": "Y",
        "전공자정원포함여부": "Y",
        "신청과목수": "6",
        "졸업신청": "N",
        "초수강여부": "Y",
        "총이수학점/졸업이수학점": "0.7857",
        "직전학기이수학점/학기당수강학점": "0.7894",
        "학년": "4",
        "수강여부": "O",
        "비고": ""
      },
      {
        "순위": "9",
        "마일리지": "5",
        "전공자/복수전공자": "Y",
        "전공자정원포함여부": "Y",
        "신청과목수": "6",
        "졸업신청": "N",
        "초수강여부": "Y",
        "총이수학점/졸업이수학점": "0.8178",
        "직전학기이수학점/학기당수강학점": "1.0000",
        "학년": "4",
        "수강여부": "O",
        "비고": ""
      },
      {
        "순위": "10",
        "마일리지": "5",
        "전공자/복수전공자": "Y",
        "전공자정원포함여부": "Y",
        "신청과목수": "6",
        "졸업신청": "N",
        "초수강여부": "Y",
        "총이수학점/졸업이수학점": "0.7785",
        "직전학기이수학점/학기당수강학점": "0.9473",
        "학년": "4",
        "수강여부": "O",
        "비고": ""
      },
      {
        "순위": "11",
        "마일리지": "5",
        "전공자/복수전공자": "Y",
        "전공자정원포함여부": "Y",
        "신청과목수": "6",
        "졸업신청": "N",
        "초수강여부": "Y",
        "총이수학점/졸업이수학점": "0.5000",
        "직전학기이수학점/학기당수강학점": "0.9210",
        "학년": "3",
        "수강여부": "O",
        "비고": ""
      },
      {
        "순위": "12",
        "마일리지": "5",
        "전공자/복수전공자": "Y",
        "전공자정원포함여부": "Y",
        "신청과목수": "5",
        "졸업신청": "N",
        "초수강여부": "Y",
        "총이수학점/졸업이수학점": "0.5000",
        "직전학기이수학점/학기당수강학점": "0.9210",
        "학년": "3",
        "수강여부": "O",
        "비고": ""
      },
      {
        "순위": "13",
        "마일리지": "4",
        "전공자/복수전공자": "Y",
        "전공자정원포함여부": "Y",
        "신청과목수": "6",
        "졸업신청": "N",
        "초수강여부": "Y",
        "총이수학점/졸업이수학점": "0.8321",
        "직전학기이수학점/학기당수강학점": "1.0000",
        "학년": "4",
        "수강여부": "O",
        "비고": ""
      },
      {
        "순위": "14",
        "마일리지": "3",
        "전공자/복수전공자": "Y",
        "전공자정원포함여부": "Y",
        "신청과목수": "6",
        "졸업신청": "N",
        "초수강여부": "Y",
        "총이수학점/졸업이수학점": "0.7642",
        "직전학기이수학점/학기당수강학점": "0.9736",
        "학년": "4",
        "수강여부": "O",
        "비고": ""
      },
      {
        "순위": "15",
        "마일리지": "2",
        "전공자/복수전공자": "Y",
        "전공자정원포함여부": "Y",
        "신청과목수": "6",
        "졸업신청": "Y",
        "초수강여부": "Y",
        "총이수학점/졸업이수학점": "0.9785",
        "직전학기이수학점/학기당수강학점": "0.9473",
        "학년": "4",
        "수강여부": "O",
        "비고": ""
      },
      {
        "순위": "16",
        "마일리지": "2",
        "전공자/복수전공자": "Y",
        "전공자정원포함여부": "Y",
        "신청과목수": "5",
        "졸업신청": "Y",
        "초수강여부": "Y",
        "총이수학점/졸업이수학점": "0.8928",
        "직전학기이수학점/학기당수강학점": "1.0000",
        "학년": "4",
        "수강여부": "O",
        "비고": ""
      },
      {
        "순위": "17",
        "마일리지": "1",
        "전공자/복수전공자": "Y",
        "전공자정원포함여부": "Y",
        "신청과목수": "6",
        "졸업신청": "Y",
        "초수강여부": "Y",
        "총이수학점/졸업이수학점": "1.0000",
        "직전학기이수학점/학기당수강학점": "0.5263",
        "학년": "4",
        "수강여부": "O",
        "비고": ""
      },
      {
        "순위": "18",
        "마일리지": "1",
        "전공자/복수전공자": "Y",
        "전공자정원포함여부": "Y",
        "신청과목수": "6",
        "졸업신청": "N",
        "초수강여부": "Y",
        "총이수학점/졸업이수학점": "0.8071",
        "직전학기이수학점/학기당수강학점": "0.9473",
        "학년": "4",
        "수강여부": "O",
        "비고": ""
      },
      {
        "순위": "19",
        "마일리지": "1",
        "전공자/복수전공자": "Y",
        "전공자정원포함여부": "Y",
        "신청과목수": "6",
        "졸업신청": "N",
        "초수강여부": "Y",
        "총이수학점/졸업이수학점": "0.7714",
        "직전학기이수학점/학기당수강학점": "0.9736",
        "학년": "4",
        "수강여부": "O",
        "비고": ""
      },
      {
        "순위": "20",
        "마일리지": "1",
        "전공자/복수전공자": "Y",
        "전공자정원포함여부": "Y",
        "신청과목수": "6",
        "졸업신청": "N",
        "초수강여부": "Y",
        "총이수학점/졸업이수학점": "0.7500",
        "직전학기이수학점/학기당수강학점": "0.9473",
        "학년": "4",
        "수강여부": "O",
        "비고": ""
      },
      {
        "순위": "21",
        "마일리지": "1",
        "전공자/복수전공자": "Y",
        "전공자정원포함여부": "Y",
        "신청과목수": "6",
        "졸업신청": "N",
        "초수강여부": "Y",
        "총이수학점/졸업이수학점": "0.6142",
        "직전학기이수학점/학기당수강학점": "0.9473",
        "학년": "3",
        "수강여부": "O",
        "비고": ""
      },
      {
        "순위": "22",
        "마일리지": "1",
        "전공자/복수전공자": "Y",
        "전공자정원포함여부": "Y",
        "신청과목수": "6",
        "졸업신청": "N",
        "초수강여부": "Y",
        "총이수학점/졸업이수학점": "0.5928",
        "직전학기이수학점/학기당수강학점": "1.0000",
        "학년": "3",
        "수강여부": "O",
        "비고": ""
      },
      {
        "순위": "23",
        "마일리지": "1",
        "전공자/복수전공자": "Y",
        "전공자정원포함여부": "Y",
        "신청과목수": "6",
        "졸업신청": "N",
        "초수강여부": "Y",
        "총이수학점/졸업이수학점": "0.5428",
        "직전학기이수학점/학기당수강학점": "0.8684",
        "학년": "3",
        "수강여부": "O",
        "비고": ""
      },
      {
        "순위": "24",
        "마일리지": "1",
        "전공자/복수전공자": "Y",
        "전공자정원포함여부": "Y",
        "신청과목수": "6",
        "졸업신청": "N",
        "초수강여부": "Y",
        "총이수학점/졸업이수학점": "0.5000",
        "직전학기이수학점/학기당수강학점": "0.9210",
        "학년": "3",
        "수강여부": "O",
        "비고": ""
      },
      {
        "순위": "25",
        "마일리지": "1",
        "전공자/복수전공자": "Y",
        "전공자정원포함여부": "Y",
        "신청과목수": "6",
        "졸업신청": "N",
        "초수강여부": "Y",
        "총이수학점/졸업이수학점": "0.5000",
        "직전학기이수학점/학기당수강학점": "0.9210",
        "학년": "3",
        "수강여부": "O",
        "비고": ""
      },
      {
        "순위": "26",
        "마일리지": "1",
        "전공자/복수전공자": "Y",
        "전공자정원포함여부": "Y",
        "신청과목수": "6",
        "졸업신청": "N",
        "초수강여부": "Y",
        "총이수학점/졸업이수학점": "0.5000",
        "직전학기이수학점/학기당수강학점": "0.9210",
        "학년": "3",
        "수강여부": "O",
        "비고": ""
      },
      {
        "순위": "27",
        "마일리지": "1",
        "전공자/복수전공자": "Y",
        "전공자정원포함여부": "Y",
        "신청과목수": "6",
        "졸업신청": "N",
        "초수강여부": "Y",
        "총이수학점/졸업이수학점": "0.4928",
        "직전학기이수학점/학기당수강학점": "0.8947",
        "학년": "3",
        "수강여부": "O",
        "비고": ""
      },
      {
        "순위": "28",
        "마일리지": "1",
        "전공자/복수전공자": "Y",
        "전공자정원포함여부": "Y",
        "신청과목수": "6",
        "졸업신청": "N",
        "초수강여부": "Y",
        "총이수학점/졸업이수학점": "0.4785",
        "직전학기이수학점/학기당수강학점": "0.8421",
        "학년": "3",
        "수강여부": "O",
        "비고": ""
      },
      {
        "순위": "29",
        "마일리지": "1",
        "전공자/복수전공자": "Y",
        "전공자정원포함여부": "Y",
        "신청과목수": "6",
        "졸업신청": "N",
        "초수강여부": "Y",
        "총이수학점/졸업이수학점": "0.4035",
        "직전학기이수학점/학기당수강학점": "1.0000",
        "학년": "2",
        "수강여부": "O",
        "비고": ""
      },
      {
        "순위": "30",
        "마일리지": "1",
        "전공자/복수전공자": "N",
        "전공자정원포함여부": "N",
        "신청과목수": "6",
        "졸업신청": "Y",
        "초수강여부": "Y",
        "총이수학점/졸업이수학점": "0.9365",
        "직전학기이수학점/학기당수강학점": "0.9473",
        "학년": "4",
        "수강여부": "O",
        "비고": ""
      }
    ]
  },
  "20201": {
    "CAUTION": {
      "생명시스템대학": {
        "생명공학전공": [
          "절대평가"
        ]
      }
    },
    "LECT_DATA": {
      "학정번호-분반-실습": "BTE3104-01-00",
      "과목명": "의약생물소재화학",
      "학점": "3",
      "담당교수": "한균희",
      "강의시간": "월6,목6,7",
      "강의실": "공A579",
      "정원": "30",
      "참여인원": "25",
      "전공자정원": "0",
      "2전공포함": "N",
      "1학년정원": "0",
      "2학년정원": "0",
      "3학년정원": "0",
      "4학년정원": "0",
      "교환학생 가능여부": "O",
      "Max Mileage(limit)": "36",
      "Mileage_minimum": "1",
      "Mileage_maximum": "36",
      "Mileage_average": "8.4"
    },
    "RESULT_DATA": [
      {
        "순위": "1",
        "마일리지": "36",
        "전공자/복수전공자": "Y",
        "전공자정원포함여부": "Y",
        "신청과목수": "6",
        "졸업신청": "N",
        "초수강여부": "Y",
        "총이수학점/졸업이수학점": "0.8071",
        "직전학기이수학점/학기당수강학점": "0.7894",
        "학년": "4",
        "수강여부": "O",
        "비고": ""
      },
      {
        "순위": "2",
        "마일리지": "20",
        "전공자/복수전공자": "Y",
        "전공자정원포함여부": "Y",
        "신청과목수": "6",
        "졸업신청": "N",
        "초수강여부": "Y",
        "총이수학점/졸업이수학점": "0.6714",
        "직전학기이수학점/학기당수강학점": "1.0000",
        "학년": "3",
        "수강여부": "O",
        "비고": ""
      },
      {
        "순위": "3",
        "마일리지": "20",
        "전공자/복수전공자": "Y",
        "전공자정원포함여부": "Y",
        "신청과목수": "3",
        "졸업신청": "Y",
        "초수강여부": "Y",
        "총이수학점/졸업이수학점": "0.9357",
        "직전학기이수학점/학기당수강학점": "0.7894",
        "학년": "4",
        "수강여부": "O",
        "비고": ""
      },
      {
        "순위": "4",
        "마일리지": "14",
        "전공자/복수전공자": "Y",
        "전공자정원포함여부": "Y",
        "신청과목수": "6",
        "졸업신청": "N",
        "초수강여부": "Y",
        "총이수학점/졸업이수학점": "0.5428",
        "직전학기이수학점/학기당수강학점": "0.9736",
        "학년": "3",
        "수강여부": "O",
        "비고": ""
      },
      {
        "순위": "5",
        "마일리지": "13",
        "전공자/복수전공자": "Y",
        "전공자정원포함여부": "Y",
        "신청과목수": "6",
        "졸업신청": "N",
        "초수강여부": "Y",
        "총이수학점/졸업이수학점": "0.5285",
        "직전학기이수학점/학기당수강학점": "0.8157",
        "학년": "3",
        "수강여부": "O",
        "비고": ""
      },
      {
        "순위": "6",
        "마일리지": "11",
        "전공자/복수전공자": "Y",
        "전공자정원포함여부": "N",
        "신청과목수": "6",
        "졸업신청": "N",
        "초수강여부": "Y",
        "총이수학점/졸업이수학점": "0.8592",
        "직전학기이수학점/학기당수강학점": "1.0000",
        "학년": "4",
        "수강여부": "O",
        "비고": ""
      },
      {
        "순위": "7",
        "마일리지": "10",
        "전공자/복수전공자": "Y",
        "전공자정원포함여부": "Y",
        "신청과목수": "6",
        "졸업신청": "N",
        "초수강여부": "Y",
        "총이수학점/졸업이수학점": "0.8714",
        "직전학기이수학점/학기당수강학점": "1.0000",
        "학년": "4",
        "수강여부": "O",
        "비고": ""
      },
      {
        "순위": "8",
        "마일리지": "10",
        "전공자/복수전공자": "Y",
        "전공자정원포함여부": "Y",
        "신청과목수": "6",
        "졸업신청": "N",
        "초수강여부": "Y",
        "총이수학점/졸업이수학점": "0.4571",
        "직전학기이수학점/학기당수강학점": "0.7894",
        "학년": "3",
        "수강여부": "O",
        "비고": ""
      },
      {
        "순위": "9",
        "마일리지": "9",
        "전공자/복수전공자": "Y",
        "전공자정원포함여부": "Y",
        "신청과목수": "6",
        "졸업신청": "N",
        "초수강여부": "Y",
        "총이수학점/졸업이수학점": "0.5000",
        "직전학기이수학점/학기당수강학점": "0.9210",
        "학년": "3",
        "수강여부": "O",
        "비고": ""
      },
      {
        "순위": "10",
        "마일리지": "9",
        "전공자/복수전공자": "Y",
        "전공자정원포함여부": "Y",
        "신청과목수": "6",
        "졸업신청": "N",
        "초수강여부": "Y",
        "총이수학점/졸업이수학점": "0.5000",
        "직전학기이수학점/학기당수강학점": "0.9210",
        "학년": "3",
        "수강여부": "O",
        "비고": ""
      },
      {
        "순위": "11",
        "마일리지": "8",
        "전공자/복수전공자": "Y",
        "전공자정원포함여부": "N",
        "신청과목수": "6",
        "졸업신청": "N",
        "초수강여부": "Y",
        "총이수학점/졸업이수학점": "0.8095",
        "직전학기이수학점/학기당수강학점": "0.8333",
        "학년": "4",
        "수강여부": "O",
        "비고": ""
      },
      {
        "순위": "12",
        "마일리지": "8",
        "전공자/복수전공자": "Y",
        "전공자정원포함여부": "Y",
        "신청과목수": "6",
        "졸업신청": "N",
        "초수강여부": "Y",
        "총이수학점/졸업이수학점": "0.5428",
        "직전학기이수학점/학기당수강학점": "0.6578",
        "학년": "3",
        "수강여부": "O",
        "비고": ""
      },
      {
        "순위": "13",
        "마일리지": "8",
        "전공자/복수전공자": "Y",
        "전공자정원포함여부": "Y",
        "신청과목수": "6",
        "졸업신청": "N",
        "초수강여부": "Y",
        "총이수학점/졸업이수학점": "0.4785",
        "직전학기이수학점/학기당수강학점": "0.6578",
        "학년": "3",
        "수강여부": "O",
        "비고": ""
      },
      {
        "순위": "14",
        "마일리지": "8",
        "전공자/복수전공자": "Y",
        "전공자정원포함여부": "Y",
        "신청과목수": "5",
        "졸업신청": "N",
        "초수강여부": "Y",
        "총이수학점/졸업이수학점": "0.9285",
        "직전학기이수학점/학기당수강학점": "0.8421",
        "학년": "4",
        "수강여부": "O",
        "비고": ""
      },
      {
        "순위": "15",
        "마일리지": "6",
        "전공자/복수전공자": "Y",
        "전공자정원포함여부": "Y",
        "신청과목수": "6",
        "졸업신청": "N",
        "초수강여부": "Y",
        "총이수학점/졸업이수학점": "0.7357",
        "직전학기이수학점/학기당수강학점": "0.7894",
        "학년": "4",
        "수강여부": "O",
        "비고": ""
      },
      {
        "순위": "16",
        "마일리지": "4",
        "전공자/복수전공자": "Y",
        "전공자정원포함여부": "Y",
        "신청과목수": "6",
        "졸업신청": "N",
        "초수강여부": "Y",
        "총이수학점/졸업이수학점": "0.6000",
        "직전학기이수학점/학기당수강학점": "0.9736",
        "학년": "3",
        "수강여부": "O",
        "비고": ""
      },
      {
        "순위": "17",
        "마일리지": "4",
        "전공자/복수전공자": "Y",
        "전공자정원포함여부": "Y",
        "신청과목수": "6",
        "졸업신청": "N",
        "초수강여부": "Y",
        "총이수학점/졸업이수학점": "0.5250",
        "직전학기이수학점/학기당수강학점": "0.8947",
        "학년": "3",
        "수강여부": "O",
        "비고": ""
      },
      {
        "순위": "18",
        "마일리지": "3",
        "전공자/복수전공자": "Y",
        "전공자정원포함여부": "Y",
        "신청과목수": "6",
        "졸업신청": "N",
        "초수강여부": "Y",
        "총이수학점/졸업이수학점": "0.4892",
        "직전학기이수학점/학기당수강학점": "0.8157",
        "학년": "3",
        "수강여부": "O",
        "비고": ""
      },
      {
        "순위": "19",
        "마일리지": "2",
        "전공자/복수전공자": "Y",
        "전공자정원포함여부": "Y",
        "신청과목수": "6",
        "졸업신청": "Y",
        "초수강여부": "Y",
        "총이수학점/졸업이수학점": "1.0000",
        "직전학기이수학점/학기당수강학점": "1.0000",
        "학년": "4",
        "수강여부": "O",
        "비고": ""
      },
      {
        "순위": "20",
        "마일리지": "2",
        "전공자/복수전공자": "Y",
        "전공자정원포함여부": "Y",
        "신청과목수": "6",
        "졸업신청": "N",
        "초수강여부": "Y",
        "총이수학점/졸업이수학점": "0.5285",
        "직전학기이수학점/학기당수강학점": "0.9210",
        "학년": "3",
        "수강여부": "O",
        "비고": ""
      },
      {
        "순위": "21",
        "마일리지": "1",
        "전공자/복수전공자": "Y",
        "전공자정원포함여부": "Y",
        "신청과목수": "6",
        "졸업신청": "N",
        "초수강여부": "Y",
        "총이수학점/졸업이수학점": "0.8071",
        "직전학기이수학점/학기당수강학점": "0.7894",
        "학년": "4",
        "수강여부": "O",
        "비고": ""
      },
      {
        "순위": "22",
        "마일리지": "1",
        "전공자/복수전공자": "Y",
        "전공자정원포함여부": "Y",
        "신청과목수": "6",
        "졸업신청": "N",
        "초수강여부": "Y",
        "총이수학점/졸업이수학점": "0.7857",
        "직전학기이수학점/학기당수강학점": "1.0000",
        "학년": "4",
        "수강여부": "O",
        "비고": ""
      },
      {
        "순위": "23",
        "마일리지": "1",
        "전공자/복수전공자": "Y",
        "전공자정원포함여부": "Y",
        "신청과목수": "6",
        "졸업신청": "N",
        "초수강여부": "Y",
        "총이수학점/졸업이수학점": "0.5892",
        "직전학기이수학점/학기당수강학점": "0.9736",
        "학년": "3",
        "수강여부": "O",
        "비고": ""
      },
      {
        "순위": "24",
        "마일리지": "1",
        "전공자/복수전공자": "Y",
        "전공자정원포함여부": "Y",
        "신청과목수": "6",
        "졸업신청": "N",
        "초수강여부": "Y",
        "총이수학점/졸업이수학점": "0.5000",
        "직전학기이수학점/학기당수강학점": "1.0000",
        "학년": "3",
        "수강여부": "O",
        "비고": ""
      },
      {
        "순위": "25",
        "마일리지": "1",
        "전공자/복수전공자": "Y",
        "전공자정원포함여부": "Y",
        "신청과목수": "5",
        "졸업신청": "Y",
        "초수강여부": "Y",
        "총이수학점/졸업이수학점": "0.9428",
        "직전학기이수학점/학기당수강학점": "1.0000",
        "학년": "4",
        "수강여부": "O",
        "비고": ""
      }
    ]
  }
}